<?xml version="1.0"?>
<user><language>en</language>


User contributions for Chiefmagoo - Wikipedia
document.documentElement.className="client-js";RLCONF={"wgBreakFrames":!1,"wgSeparatorTransformTable":["",""],"wgDigitTransformTable":["",""],"wgDefaultDateFormat":"dmy","wgMonthNames":["","January","February","March","April","May","June","July","August","September","October","November","December"],"wgRequestId":"c75e0504-5d02-40b2-b2f0-1292dbb487e2","wgCSPNonce":!1,"wgCanonicalNamespace":"Special","wgCanonicalSpecialPageName":"Contributions","wgNamespaceNumber":-1,"wgPageName":"Special:Contributions","wgTitle":"Contributions","wgCurRevisionId":0,"wgRevisionId":0,"wgArticleId":0,"wgIsArticle":!1,"wgIsRedirect":!1,"wgAction":"view","wgUserName":null,"wgUserGroups":["*"],"wgCategories":[],"wgPageContentLanguage":"en","wgPageContentModel":"wikitext","wgRelevantPageName":"Special:Contributions","wgRelevantArticleId":0,"wgIsProbablyEditable":!1,"wgRelevantPageIsProbablyEditable":!1,"wgRelevantUserName":"Chiefmagoo","wgMediaViewerOnClick":!0,
"wgMediaViewerEnabledByDefault":!0,"wgPopupsReferencePreviews":!1,"wgPopupsConflictsWithNavPopupGadget":!1,"wgVisualEditor":{"pageLanguageCode":"en","pageLanguageDir":"ltr","pageVariantFallbacks":"en"},"wgMFDisplayWikibaseDescriptions":{"search":!0,"nearby":!0,"watchlist":!0,"tagline":!1},"wgWMESchemaEditAttemptStepOversample":!1,"wgULSCurrentAutonym":"English","wgNoticeProject":"wikipedia","wgCentralAuthMobileDomain":!1,"wgEditSubmitButtonLabelPublish":!0,"wgULSPosition":"interlanguage"};RLSTATE={"ext.globalCssJs.user.styles":"ready","site.styles":"ready","noscript":"ready","user.styles":"ready","ext.globalCssJs.user":"ready","user":"ready","user.options":"loading","jquery.makeCollapsible.styles":"ready","mediawiki.interface.helpers.styles":"ready","mediawiki.special":"ready","mediawiki.special.changeslist":"ready","mediawiki.helplink":"ready","mediawiki.widgets.DateInputWidget.styles":"ready","oojs-ui-core.styles":"ready","oojs-ui.styles.indicators":"ready",
"mediawiki.widgets.styles":"ready","oojs-ui-core.icons":"ready","mediawiki.htmlform.ooui.styles":"ready","mediawiki.htmlform.styles":"ready","skins.vector.styles.legacy":"ready","mediawiki.feedlink":"ready","ext.flaggedRevs.basic":"ready","ext.visualEditor.desktopArticleTarget.noscript":"ready","ext.uls.interlanguage":"ready","ext.wikimediaBadges":"ready"};RLPAGEMODULES=["mediawiki.special.recentchanges","mediawiki.page.ready","mediawiki.special.contributions","mediawiki.htmlform","mediawiki.htmlform.ooui","mediawiki.widgets.UserInputWidget","mediawiki.widgets","oojs-ui-widgets","mediawiki.widgets.DateInputWidget","site","jquery.makeCollapsible","skins.vector.legacy.js","ext.gadget.ReferenceTooltips","ext.gadget.charinsert","ext.gadget.extra-toolbar-buttons","ext.gadget.refToolbar","ext.gadget.switcher","ext.centralauth.centralautologin","mmv.head","mmv.bootstrap.autostart","ext.popups","ext.visualEditor.desktopArticleTarget.init","ext.visualEditor.targetLoader","ext.eventLogging",
"ext.wikimediaEvents","ext.navigationTiming","ext.uls.compactlinks","ext.uls.interface","ext.cx.eventlogging.campaigns","ext.centralNotice.geoIP"];
(RLQ=window.RLQ||[]).push(function(){mw.loader.implement("user.options@1hzgi",function($,jQuery,require,module){/*@nomin*/mw.user.tokens.set({"patrolToken":"+\\","watchToken":"+\\","csrfToken":"+\\"});
});});
















<name>Chiefmagoo</name>





	
	
	
	Help
	
	User contributions
	
		
		For Chiefmagoo talk block log uploads logs filter log
		
		
		
		Jump to navigation
		Jump to search
		Search for contributionsshowhide⧼contribs-top⧽User:Namespace:all(Article)TalkUserUser talkWikipediaWikipedia talkFileFile talkMediaWikiMediaWiki talkTemplateTemplate talkHelpHelp talkCategoryCategory talkPortalPortal talkBookBook talkDraftDraft talkEducation ProgramEducation Program talkTimedTextTimedText talkModuleModule talkGadgetGadget talkGadget definitionGadget definition talkInvert selectionAssociated namespaceTag filter:Only show edits that are latest revisionsOnly show edits that are page creationsHide minor edits⧼contribs-date⧽From date:To date:
Hide probably good edits


Search
<versions><version><id>377568631</id><timestamp>00:19, 7 August 2010</timestamp><title>Double-elimination tournament</title><comment/></version><version><id>377568544</id><timestamp>00:18, 7 August 2010</timestamp><title>Double-elimination tournament</title><comment/></version><version><id>377568127</id><timestamp>00:14, 7 August 2010</timestamp><title>User:Chiefmagoo</title><comment/></version><version><id>377567429</id><timestamp>00:09, 7 August 2010</timestamp><title>2010 Little League World Series</title><comment/></version><version><id>343513535</id><timestamp>08:54, 12 February 2010</timestamp><title>Vicente San Bruno</title><comment/></version><version><id>309674657</id><timestamp>22:30, 23 August 2009</timestamp><title>2009 Little League World Series</title><comment/></version><version><id>303089186</id><timestamp>07:11, 20 July 2009</timestamp><title>Iceland–European Union relations</title><comment/></version><version><id>295134095</id><timestamp>08:07, 8 June 2009</timestamp><title>The Mighty Ducks</title><comment/></version><version><id>294448071</id><timestamp>20:51, 4 June 2009</timestamp><title>1989 Tiananmen Square protests</title><comment/></version><version><id>289434454</id><timestamp>10:12, 12 May 2009</timestamp><title>ESPN MLS GameNight</title><comment/></version><version><id>288805968</id><timestamp>04:09, 9 May 2009</timestamp><title>Super Bowl</title><comment/></version><version><id>287804800</id><timestamp>08:12, 4 May 2009</timestamp><title>2005–06 NFL playoffs</title><comment/></version><version><id>287803403</id><timestamp>07:57, 4 May 2009</timestamp><title>Browns–Steelers rivalry</title><comment/></version><version><id>263997899</id><timestamp>08:31, 14 January 2009</timestamp><title>2005–06 NFL playoffs</title><comment/></version><version><id>261995481</id><timestamp>00:30, 5 January 2009</timestamp><title>2008–09 NFL playoffs</title><comment/></version><version><id>260648860</id><timestamp>10:11, 29 December 2008</timestamp><title>2008 Arizona Cardinals season</title><comment/></version><version><id>259795287</id><timestamp>22:05, 23 December 2008</timestamp><title>AFC North</title><comment/></version><version><id>251712770</id><timestamp>04:52, 14 November 2008</timestamp><title>John Shadegg</title><comment/></version><version><id>233014981</id><timestamp>00:34, 20 August 2008</timestamp><title>2008 Little League World Series</title><comment/></version><version><id>232979404</id><timestamp>20:48, 19 August 2008</timestamp><title>2008 Little League World Series</title><comment/></version><version><id>232978074</id><timestamp>20:41, 19 August 2008</timestamp><title>2008 Little League World Series</title><comment/></version><version><id>232781747</id><timestamp>22:34, 18 August 2008</timestamp><title>2008 Little League World Series</title><comment/></version><version><id>232781282</id><timestamp>22:32, 18 August 2008</timestamp><title>2008 Little League World Series</title><comment/></version><version><id>232781096</id><timestamp>22:31, 18 August 2008</timestamp><title>2008 Little League World Series</title><comment/></version><version><id>232780516</id><timestamp>22:27, 18 August 2008</timestamp><title>2008 Little League World Series</title><comment/></version><version><id>232765720</id><timestamp>21:04, 18 August 2008</timestamp><title>2008 Little League World Series</title><comment/></version><version><id>232678066</id><timestamp>12:56, 18 August 2008</timestamp><title>2008 Little League World Series</title><comment/></version><version><id>229359181</id><timestamp>05:18, 2 August 2008</timestamp><title>User:Chiefmagoo</title><comment/></version><version><id>211531476</id><timestamp>21:02, 10 May 2008</timestamp><title>1964 Republican National Convention</title><comment/></version><version><id>211400927</id><timestamp>04:15, 10 May 2008</timestamp><title>Hogan Knows Best</title><comment/></version><version><id>210528905</id><timestamp>09:06, 6 May 2008</timestamp><title>2005 Little League World Series</title><comment/></version><version><id>207292026</id><timestamp>04:58, 22 April 2008</timestamp><title>Iran–Iraq War</title><comment/></version><version><id>206393248</id><timestamp>01:29, 18 April 2008</timestamp><title>2008 Masters Tournament</title><comment/></version><version><id>205021197</id><timestamp>22:53, 11 April 2008</timestamp><title>WesBanco Arena</title><comment/></version><version><id>202130657</id><timestamp>20:20, 30 March 2008</timestamp><title>2008 NCAA Division I Men's Basketball Tournament</title><comment/></version><version><id>198112764</id><timestamp>02:56, 14 March 2008</timestamp><title>User:Chiefmagoo</title><comment/></version><version><id>198108119</id><timestamp>02:25, 14 March 2008</timestamp><title>User:Chiefmagoo</title><comment/></version><version><id>198107706</id><timestamp>02:23, 14 March 2008</timestamp><title>User:Chiefmagoo</title><comment/></version><version><id>191961815</id><timestamp>00:34, 17 February 2008</timestamp><title>Bowl Championship Series</title><comment/></version><version><id>191958994</id><timestamp>00:18, 17 February 2008</timestamp><title>Pac-12 Conference</title><comment/></version><version><id>180689768</id><timestamp>22:29, 28 December 2007</timestamp><title>1978–79 NFL playoffs</title><comment/></version><version><id>178633370</id><timestamp>02:13, 18 December 2007</timestamp><title>Maroon</title><comment/></version><version><id>178382418</id><timestamp>22:38, 16 December 2007</timestamp><title>Football Night in America</title><comment/></version><version><id>174325096</id><timestamp>08:00, 28 November 2007</timestamp><title>Sierra Leone</title><comment/></version><version><id>161516317</id><timestamp>10:24, 1 October 2007</timestamp><title>2007 American League Division Series</title><comment/></version><version><id>155392319</id><timestamp>11:04, 3 September 2007</timestamp><title>1985 Oregon State vs. Washington football game</title><comment/></version><version><id>155156544</id><timestamp>05:17, 2 September 2007</timestamp><title>Wikipedia:Articles for deletion/2007 Appalachian State vs. Michigan football game</title><comment/></version><version><id>155155696</id><timestamp>05:09, 2 September 2007</timestamp><title>Wikipedia:Articles for deletion/2007 Appalachian State vs. Michigan football game</title><comment/></version><version><id>155155488</id><timestamp>05:08, 2 September 2007</timestamp><title>Wikipedia:Articles for deletion/2007 Appalachian State vs. Michigan football game</title><comment/></version><version><id>155155382</id><timestamp>05:07, 2 September 2007</timestamp><title>Wikipedia:Articles for deletion/2007 Appalachian State vs. Michigan football game</title><comment/></version><version><id>155154774</id><timestamp>05:03, 2 September 2007</timestamp><title>Wikipedia:Articles for deletion/2007 Appalachian State vs. Michigan football game</title><comment/></version><version><id>155154748</id><timestamp>05:02, 2 September 2007</timestamp><title>Wikipedia:Articles for deletion/2007 Appalachian State vs. Michigan football game</title><comment/></version><version><id>155106127</id><timestamp>23:08, 1 September 2007</timestamp><title>Lloyd Carr</title><comment/></version><version><id>153894879</id><timestamp>05:53, 27 August 2007</timestamp><title>The Mighty Ducks</title><comment/></version><version><id>153893676</id><timestamp>05:41, 27 August 2007</timestamp><title>The Mighty Ducks</title><comment/></version><version><id>152819303</id><timestamp>01:25, 22 August 2007</timestamp><title>2007 Little League World Series</title><comment/></version><version><id>152819225</id><timestamp>01:24, 22 August 2007</timestamp><title>2007 Little League World Series</title><comment/></version><version><id>152368437</id><timestamp>01:49, 20 August 2007</timestamp><title>2007 Little League World Series</title><comment/></version><version><id>152367989</id><timestamp>01:47, 20 August 2007</timestamp><title>2007 Little League World Series</title><comment/></version><version><id>152327473</id><timestamp>21:55, 19 August 2007</timestamp><title>2007 Little League World Series</title><comment/></version><version><id>152327339</id><timestamp>21:54, 19 August 2007</timestamp><title>2007 Little League World Series</title><comment/></version><version><id>152325190</id><timestamp>21:43, 19 August 2007</timestamp><title>2007 Little League World Series</title><comment/></version><version><id>152325142</id><timestamp>21:43, 19 August 2007</timestamp><title>2007 Little League World Series</title><comment/></version><version><id>152324696</id><timestamp>21:40, 19 August 2007</timestamp><title>2007 Little League World Series</title><comment/></version><version><id>152288495</id><timestamp>18:19, 19 August 2007</timestamp><title>2007 Little League World Series results</title><comment/></version><version><id>152288318</id><timestamp>18:18, 19 August 2007</timestamp><title>2007 Little League World Series results</title><comment/></version><version><id>152288046</id><timestamp>18:17, 19 August 2007</timestamp><title>2007 Little League World Series</title><comment/></version><version><id>152287596</id><timestamp>18:14, 19 August 2007</timestamp><title>2007 Little League World Series</title><comment/></version><version><id>152286885</id><timestamp>18:11, 19 August 2007</timestamp><title>2007 Little League World Series</title><comment/></version><version><id>152286568</id><timestamp>18:09, 19 August 2007</timestamp><title>2007 Little League World Series</title><comment/></version><version><id>152099431</id><timestamp>20:07, 18 August 2007</timestamp><title>2007 Little League World Series</title><comment/></version><version><id>152098404</id><timestamp>20:01, 18 August 2007</timestamp><title>2007 Little League World Series</title><comment/></version><version><id>152098100</id><timestamp>19:59, 18 August 2007</timestamp><title>2007 Little League World Series</title><comment/></version><version><id>146937961</id><timestamp>06:16, 25 July 2007</timestamp><title>Arizona State Sun Devils football</title><comment/></version><version><id>146026009</id><timestamp>23:42, 20 July 2007</timestamp><title>Steubenville High School</title><comment/></version><version><id>143171162</id><timestamp>21:53, 7 July 2007</timestamp><title>Himno Nacional Mexicano</title><comment/></version><version><id>141560387</id><timestamp>07:35, 30 June 2007</timestamp><title>Incidents at Six Flags parks</title><comment/></version><version><id>139758939</id><timestamp>21:24, 21 June 2007</timestamp><title>User:Chiefmagoo</title><comment/></version><version><id>139758615</id><timestamp>21:22, 21 June 2007</timestamp><title>Wikipedia:WikiProject College baseball</title><comment/></version><version><id>138206439</id><timestamp>20:22, 14 June 2007</timestamp><title>Katie Volding</title><comment/></version><version><id>138206135</id><timestamp>20:21, 14 June 2007</timestamp><title>Katie Volding</title><comment/></version><version><id>138206088</id><timestamp>20:21, 14 June 2007</timestamp><title>Katie Volding</title><comment/></version><version><id>137524361</id><timestamp/><title>2007 College World Series</title><comment/></version><version><id>137372363</id><timestamp/><title>2007 College World Series</title><comment/></version><version><id>137372232</id><timestamp/><title>2007 College World Series</title><comment/></version><version><id>137371616</id><timestamp/><title>2007 College World Series</title><comment/></version><version><id>137370042</id><timestamp/><title>2007 College World Series</title><comment/></version><version><id>137369170</id><timestamp>02:17, 11 June 2007</timestamp><title>2007 NCAA Division I Baseball Tournament</title><comment/></version><version><id>137369004</id><timestamp/><title>2007 College World Series</title><comment/></version><version><id>137368855</id><timestamp/><title>2007 College World Series</title><comment/></version><version><id>137303795</id><timestamp/><title>2007 College World Series</title><comment/></version><version><id>137303759</id><timestamp/><title>2007 College World Series</title><comment/></version><version><id>137156516</id><timestamp/><title>2007 College World Series</title><comment/></version><version><id>137156450</id><timestamp/><title>2007 College World Series</title><comment/></version><version><id>137156259</id><timestamp/><title>2007 College World Series</title><comment/></version><version><id>137155874</id><timestamp/><title>2007 College World Series</title><comment/></version><version><id>137155836</id><timestamp/><title>2007 College World Series</title><comment/></version><version><id>137153819</id><timestamp>01:08, 10 June 2007</timestamp><title>2007 NCAA Division I Baseball Tournament</title><comment/></version><version><id>137153723</id><timestamp/><title>2007 College World Series</title><comment/></version><version><id>137095833</id><timestamp/><title>2007 College World Series</title><comment/></version><version><id>136906843</id><timestamp>20:48, 8 June 2007</timestamp><title>2007 NCAA Division I Baseball Tournament</title><comment/></version><version><id>136551855</id><timestamp>08:15, 7 June 2007</timestamp><title>User:Chiefmagoo</title><comment/></version><version><id>136012982</id><timestamp/><title>2007 College World Series</title><comment/></version><version><id>135726991</id><timestamp>05:52, 4 June 2007</timestamp><title>2007 NCAA Division I Baseball Tournament</title><comment/></version><version><id>135726923</id><timestamp>05:51, 4 June 2007</timestamp><title>2007 NCAA Division I Baseball Tournament</title><comment/></version><version><id>135636122</id><timestamp>21:20, 3 June 2007</timestamp><title>Robert Horry</title><comment/></version><version><id>135485085</id><timestamp>05:09, 3 June 2007</timestamp><title>2007 NCAA Division I Baseball Tournament</title><comment/></version><version><id>134143706</id><timestamp>19:40, 28 May 2007</timestamp><title>1984 NCAA Division I-A football season</title><comment/></version><version><id>131905645</id><timestamp>00:50, 19 May 2007</timestamp><title>2006 NCAA Division I Baseball Tournament</title><comment/></version><version><id>130515973</id><timestamp>11:09, 13 May 2007</timestamp><title>Emotions (Mariah Carey song)</title><comment/></version><version><id>128039592</id><timestamp>20:15, 3 May 2007</timestamp><title>Made (TV series)</title><comment/></version><version><id>127361887</id><timestamp>07:01, 1 May 2007</timestamp><title>User:Chiefmagoo</title><comment/></version><version><id>127359812</id><timestamp>06:43, 1 May 2007</timestamp><title>Wikipedia:WikiProject National Football League</title><comment/></version><version><id>127359417</id><timestamp>06:40, 1 May 2007</timestamp><title>Wikipedia:WikiProject Baseball/Participant list</title><comment/></version><version><id>127358667</id><timestamp>06:34, 1 May 2007</timestamp><title>Wikipedia:WikiProject Television/24 task force/Participants</title><comment/></version><version><id>127358625</id><timestamp>06:34, 1 May 2007</timestamp><title>Wikipedia:WikiProject Television/24 task force/Participants</title><comment/></version><version><id>127357988</id><timestamp>06:29, 1 May 2007</timestamp><title>Wikipedia:WikiProject Internet culture</title><comment/></version><version><id>127357960</id><timestamp>06:29, 1 May 2007</timestamp><title>Wikipedia:WikiProject Internet culture</title><comment/></version><version><id>127357892</id><timestamp>06:28, 1 May 2007</timestamp><title>Wikipedia:WikiProject Internet culture</title><comment/></version><version><id>127357831</id><timestamp>06:28, 1 May 2007</timestamp><title>Wikipedia:WikiProject Internet culture</title><comment/></version><version><id>127357177</id><timestamp>06:22, 1 May 2007</timestamp><title>Wikipedia:WikiProject United States Presidents</title><comment/></version><version><id>127357143</id><timestamp>06:22, 1 May 2007</timestamp><title>Wikipedia:WikiProject United States Presidents</title><comment/></version><version><id>127355155</id><timestamp>06:05, 1 May 2007</timestamp><title>User:Chiefmagoo</title><comment/></version><version><id>127350648</id><timestamp>05:28, 1 May 2007</timestamp><title>User:Chiefmagoo</title><comment/></version><version><id>127347859</id><timestamp>05:06, 1 May 2007</timestamp><title>User:Chiefmagoo</title><comment/></version><version><id>127346509</id><timestamp>04:57, 1 May 2007</timestamp><title>User:Chiefmagoo</title><comment/></version><version><id>127328528</id><timestamp>02:54, 1 May 2007</timestamp><title>1973 Little League World Series</title><comment/></version><version><id>127327571</id><timestamp>02:49, 1 May 2007</timestamp><title>1968 Little League World Series</title><comment/></version><version><id>127326921</id><timestamp>02:46, 1 May 2007</timestamp><title>1947 Little League World Series</title><comment/></version><version><id>127270586</id><timestamp>22:54, 30 April 2007</timestamp><title>Ohio Valley Athletic Conference</title><comment/></version><version><id>126565150</id><timestamp>05:32, 28 April 2007</timestamp><title>Toronto Junior/Senior High School</title><comment/></version><version><id>124158446</id><timestamp>19:09, 19 April 2007</timestamp><title>Steubenville High School</title><comment/></version><version><id>124158388</id><timestamp>19:09, 19 April 2007</timestamp><title>Steubenville High School</title><comment/></version><version><id>124158280</id><timestamp>19:09, 19 April 2007</timestamp><title>Steubenville High School</title><comment/></version><version><id>124158202</id><timestamp>19:08, 19 April 2007</timestamp><title>Steubenville High School</title><comment/></version><version><id>124157506</id><timestamp>19:05, 19 April 2007</timestamp><title>Steubenville High School</title><comment/></version><version><id>121282959</id><timestamp>22:37, 8 April 2007</timestamp><title>Masters Tournament</title><comment/></version><version><id>121282893</id><timestamp>22:37, 8 April 2007</timestamp><title>Masters Tournament</title><comment/></version><version><id>119537910</id><timestamp>18:34, 1 April 2007</timestamp><title>Canton McKinley High School</title><comment/></version><version><id>119537799</id><timestamp>18:33, 1 April 2007</timestamp><title>Canton McKinley High School</title><comment/></version><version><id>118880090</id><timestamp>21:25, 29 March 2007</timestamp><title>Michigan–Ohio State football rivalry</title><comment/></version><version><id>116311039</id><timestamp/><title>Anya Suvarov</title><comment/></version><version><id>115245993</id><timestamp>04:17, 15 March 2007</timestamp><title>South Park</title><comment/></version><version><id>112909675</id><timestamp>22:03, 5 March 2007</timestamp><title>Toilet paper</title><comment/></version><version><id>112261571</id><timestamp>05:38, 3 March 2007</timestamp><title>Ghosts of Mississippi</title><comment/></version><version><id>112139132</id><timestamp>19:30, 2 March 2007</timestamp><title>Ninth Amendment to the United States Constitution</title><comment/></version><version><id>110714964</id><timestamp>01:04, 25 February 2007</timestamp><title>Cuba–United States relations</title><comment/></version><version><id>109478099</id><timestamp/><title>List of minor characters in 24</title><comment/></version><version><id>109477112</id><timestamp>04:13, 20 February 2007</timestamp><title>Charles Logan (24)</title><comment/></version><version><id>109135974</id><timestamp>20:21, 18 February 2007</timestamp><title>2006 Arizona State Sun Devils football team</title><comment/></version><version><id>109117060</id><timestamp>18:44, 18 February 2007</timestamp><title>List of NASCAR drivers</title><comment/></version><version><id>109114893</id><timestamp>18:33, 18 February 2007</timestamp><title>List of NASCAR drivers</title><comment/></version><version><id>109113618</id><timestamp>18:26, 18 February 2007</timestamp><title>List of NASCAR drivers</title><comment/></version><version><id>109111518</id><timestamp>18:15, 18 February 2007</timestamp><title>Bill Baker (racing driver)</title><comment/></version><version><id>109111373</id><timestamp>18:15, 18 February 2007</timestamp><title>John Anderson (racing driver)</title><comment/></version><version><id>109111337</id><timestamp>18:14, 18 February 2007</timestamp><title>John Anderson (racing driver)</title><comment/></version><version><id>106375651</id><timestamp>19:06, 7 February 2007</timestamp><title>Tom Benson Hall of Fame Stadium</title><comment/></version><version><id>104431786</id><timestamp>22:26, 30 January 2007</timestamp><title>Arizona State Sun Devils football</title><comment/></version><version><id>103564748</id><timestamp>07:41, 27 January 2007</timestamp><title>Arizona State Sun Devils football</title><comment/></version><version><id>103560193</id><timestamp>06:59, 27 January 2007</timestamp><title>Arizona State Sun Devils football</title><comment/></version><version><id>72144592</id><timestamp>06:35, 27 August 2006</timestamp><title>2006 Little League World Series</title><comment/></version><version><id>71727732</id><timestamp>02:20, 25 August 2006</timestamp><title>2006 Little League World Series</title><comment/></version><version><id>71519452</id><timestamp>03:15, 24 August 2006</timestamp><title>2006 Little League World Series</title><comment/></version><version><id>71460151</id><timestamp>21:06, 23 August 2006</timestamp><title>2006 Little League World Series</title><comment/></version><version><id>71290996</id><timestamp>01:36, 23 August 2006</timestamp><title>2006 Little League World Series</title><comment/></version><version><id>71281883</id><timestamp>00:37, 23 August 2006</timestamp><title>2006 Little League World Series</title><comment/></version><version><id>71281747</id><timestamp>00:36, 23 August 2006</timestamp><title>2006 Little League World Series</title><comment/></version><version><id>71281308</id><timestamp>00:33, 23 August 2006</timestamp><title>2006 Little League World Series</title><comment/></version><version><id>71281131</id><timestamp>00:32, 23 August 2006</timestamp><title>2006 Little League World Series</title><comment/></version><version><id>71244372</id><timestamp>21:07, 22 August 2006</timestamp><title>2006 Little League World Series</title><comment/></version><version><id>71244193</id><timestamp>21:06, 22 August 2006</timestamp><title>2006 Little League World Series</title><comment/></version><version><id>71244095</id><timestamp>21:06, 22 August 2006</timestamp><title>2006 Little League World Series</title><comment/></version><version><id>71241606</id><timestamp>20:54, 22 August 2006</timestamp><title>2006 Little League World Series</title><comment/></version><version><id>71239771</id><timestamp>20:46, 22 August 2006</timestamp><title>2006 Little League World Series</title><comment/></version><version><id>71237432</id><timestamp>20:35, 22 August 2006</timestamp><title>2006 Little League World Series</title><comment/></version><version><id>71235835</id><timestamp>20:27, 22 August 2006</timestamp><title>2006 Little League World Series</title><comment/></version><version><id>71229639</id><timestamp>19:55, 22 August 2006</timestamp><title>2006 Little League World Series</title><comment/></version><version><id>71223820</id><timestamp>19:19, 22 August 2006</timestamp><title>2006 Little League World Series</title><comment/></version><version><id>71202726</id><timestamp>17:22, 22 August 2006</timestamp><title>2006 Little League World Series</title><comment/></version><version><id>71202148</id><timestamp>17:18, 22 August 2006</timestamp><title>2006 Little League World Series</title><comment/></version><version><id>71088702</id><timestamp>02:21, 22 August 2006</timestamp><title>2006 Little League World Series</title><comment/></version><version><id>71088366</id><timestamp>02:19, 22 August 2006</timestamp><title>2006 Little League World Series</title><comment/></version><version><id>71088257</id><timestamp>02:18, 22 August 2006</timestamp><title>2006 Little League World Series</title><comment/></version><version><id>71086966</id><timestamp>02:09, 22 August 2006</timestamp><title>2006 Little League World Series</title><comment/></version><version><id>71086897</id><timestamp>02:09, 22 August 2006</timestamp><title>2006 Little League World Series</title><comment/></version><version><id>71072670</id><timestamp>00:31, 22 August 2006</timestamp><title>2006 Little League World Series</title><comment/></version><version><id>71069826</id><timestamp>00:12, 22 August 2006</timestamp><title>2006 Little League World Series</title><comment/></version><version><id>71069477</id><timestamp>00:10, 22 August 2006</timestamp><title>2006 Little League World Series</title><comment/></version><version><id>71069166</id><timestamp>00:07, 22 August 2006</timestamp><title>2006 Little League World Series</title><comment/></version><version><id>71068919</id><timestamp>00:06, 22 August 2006</timestamp><title>2006 Little League World Series</title><comment/></version><version><id>71048742</id><timestamp>22:05, 21 August 2006</timestamp><title>Pittsburgh Pirates</title><comment/></version><version><id>71042201</id><timestamp>21:30, 21 August 2006</timestamp><title>Talk:2006 Little League World Series</title><comment/></version><version><id>71041774</id><timestamp>21:27, 21 August 2006</timestamp><title>2006 Little League World Series</title><comment/></version><version><id>71041631</id><timestamp>21:27, 21 August 2006</timestamp><title>2006 Little League World Series</title><comment/></version><version><id>71039353</id><timestamp>21:13, 21 August 2006</timestamp><title>2006 Little League World Series</title><comment/></version><version><id>71036864</id><timestamp>21:00, 21 August 2006</timestamp><title>2006 Little League World Series</title><comment/></version><version><id>71036576</id><timestamp>20:59, 21 August 2006</timestamp><title>2006 Little League World Series</title><comment/></version><version><id>71017082</id><timestamp>19:21, 21 August 2006</timestamp><title>2006 Little League World Series</title><comment/></version><version><id>70992847</id><timestamp>17:23, 21 August 2006</timestamp><title>2006 Little League World Series</title><comment/></version><version><id>70992698</id><timestamp>17:23, 21 August 2006</timestamp><title>2006 Little League World Series</title><comment/></version><version><id>70992490</id><timestamp>17:22, 21 August 2006</timestamp><title>2006 Little League World Series</title><comment/></version><version><id>70992383</id><timestamp>17:21, 21 August 2006</timestamp><title>2006 Little League World Series</title><comment/></version><version><id>70992237</id><timestamp>17:20, 21 August 2006</timestamp><title>2006 Little League World Series</title><comment/></version><version><id>70991408</id><timestamp>17:16, 21 August 2006</timestamp><title>2006 Little League World Series</title><comment/></version><version><id>70991048</id><timestamp>17:15, 21 August 2006</timestamp><title>2006 Little League World Series</title><comment/></version><version><id>70990585</id><timestamp>17:12, 21 August 2006</timestamp><title>2006 Little League World Series</title><comment/></version><version><id>70879601</id><timestamp>02:12, 21 August 2006</timestamp><title>2006 Little League World Series</title><comment/></version><version><id>70879518</id><timestamp>02:11, 21 August 2006</timestamp><title>2006 Little League World Series</title><comment/></version><version><id>70874208</id><timestamp>01:34, 21 August 2006</timestamp><title>2006 Little League World Series</title><comment/></version><version><id>70874012</id><timestamp>01:33, 21 August 2006</timestamp><title>2006 Little League World Series</title><comment/></version><version><id>70858223</id><timestamp>23:46, 20 August 2006</timestamp><title>2006 Little League World Series</title><comment/></version><version><id>70843001</id><timestamp>22:14, 20 August 2006</timestamp><title>2006 Little League World Series</title><comment/></version><version><id>70809089</id><timestamp>19:07, 20 August 2006</timestamp><title>2006 Little League World Series</title><comment/></version><version><id>70799168</id><timestamp>18:11, 20 August 2006</timestamp><title>2006 Little League World Series</title><comment/></version><version><id>70798640</id><timestamp>18:07, 20 August 2006</timestamp><title>2006 Little League World Series</title><comment/></version><version><id>70788309</id><timestamp>17:05, 20 August 2006</timestamp><title>2006 Little League World Series</title><comment/></version><version><id>70729306</id><timestamp>07:52, 20 August 2006</timestamp><title>Raise Your Voice</title><comment/></version><version><id>70650862</id><timestamp>21:37, 19 August 2006</timestamp><title>2006 Little League World Series</title><comment/></version><version><id>70648291</id><timestamp>21:20, 19 August 2006</timestamp><title>2006 Little League World Series</title><comment/></version><version><id>70627253</id><timestamp>19:02, 19 August 2006</timestamp><title>2006 Little League World Series qualification</title><comment/></version><version><id>70618094</id><timestamp>18:04, 19 August 2006</timestamp><title>2006 Little League World Series</title><comment/></version><version><id>70617972</id><timestamp>18:03, 19 August 2006</timestamp><title>2006 Little League World Series</title><comment/></version><version><id>70616581</id><timestamp>17:55, 19 August 2006</timestamp><title>2006 Little League World Series</title><comment/></version><version><id>70615326</id><timestamp>17:46, 19 August 2006</timestamp><title>2006 Little League World Series</title><comment/></version><version><id>70609426</id><timestamp>17:03, 19 August 2006</timestamp><title>2006 Little League World Series</title><comment/></version><version><id>70520028</id><timestamp>02:22, 19 August 2006</timestamp><title>2006 Little League World Series</title><comment/></version><version><id>70517681</id><timestamp>02:03, 19 August 2006</timestamp><title>The Truman Show</title><comment/></version><version><id>70511138</id><timestamp>01:15, 19 August 2006</timestamp><title>2006 Little League World Series</title><comment/></version><version><id>70510775</id><timestamp>01:12, 19 August 2006</timestamp><title>2006 Little League World Series</title><comment/></version><version><id>70510366</id><timestamp>01:10, 19 August 2006</timestamp><title>2006 Little League World Series</title><comment/></version><version><id>70115445</id><timestamp>22:58, 16 August 2006</timestamp><title>Left- and right-hand traffic</title><comment/></version><version><id>70115343</id><timestamp>22:58, 16 August 2006</timestamp><title>Left- and right-hand traffic</title><comment/></version><version><id>70113989</id><timestamp>22:50, 16 August 2006</timestamp><title>California's 50th congressional district</title><comment/></version><version><id>70113918</id><timestamp>22:50, 16 August 2006</timestamp><title>Texas's 22nd congressional district</title><comment/></version><version><id>70113652</id><timestamp>22:49, 16 August 2006</timestamp><title>California's 50th congressional district</title><comment/></version><version><id>69952108</id><timestamp>04:36, 16 August 2006</timestamp><title>Rice-A-Roni</title><comment/></version><version><id>69308284</id><timestamp>01:13, 13 August 2006</timestamp><title>David Beckham</title><comment/></version><version><id>69305735</id><timestamp>00:52, 13 August 2006</timestamp><title>George Mikan</title><comment/></version><version><id>69139394</id><timestamp>02:40, 12 August 2006</timestamp><title>Dan Marino</title><comment/></version><version><id>68720339</id><timestamp>00:09, 10 August 2006</timestamp><title>1996 NCAA Division I-A football season</title><comment/></version><version><id>68668447</id><timestamp>19:13, 9 August 2006</timestamp><title>International border states of the United States</title><comment/></version><version><id>68453685</id><timestamp>19:07, 8 August 2006</timestamp><title>Steubenville Stampede</title><comment/></version><version><id>68145624</id><timestamp>06:34, 7 August 2006</timestamp><title>Trumbull, Connecticut</title><comment/></version><version><id>68145539</id><timestamp>06:33, 7 August 2006</timestamp><title>Chris Drury</title><comment/></version><version><id>66932720</id><timestamp>22:11, 31 July 2006</timestamp><title>2005 NCAA Division I-A football season</title><comment/></version><version><id>66932604</id><timestamp>22:11, 31 July 2006</timestamp><title>2005 NCAA Division I-A football season</title><comment/></version><version><id>66907526</id><timestamp>19:39, 31 July 2006</timestamp><title>Roberto Hernández (relief pitcher)</title><comment/></version><version><id>66886703</id><timestamp>17:35, 31 July 2006</timestamp><title>1998 NCAA Division I-A football season</title><comment/></version><version><id>66886653</id><timestamp>17:35, 31 July 2006</timestamp><title>1998 NCAA Division I-A football season</title><comment/></version><version><id>66884404</id><timestamp>17:20, 31 July 2006</timestamp><title>1989 NCAA Division I-A football season</title><comment/></version><version><id>66559940</id><timestamp>18:54, 29 July 2006</timestamp><title>1997 American League Division Series</title><comment/></version><version><id>66559907</id><timestamp>18:53, 29 July 2006</timestamp><title>1997 American League Division Series</title><comment/></version><version><id>65685353</id><timestamp>03:38, 25 July 2006</timestamp><title>24 (season 6)</title><comment/></version><version><id>65102050</id><timestamp>21:25, 21 July 2006</timestamp><title>Kennywood</title><comment/></version><version><id>65098053</id><timestamp>20:58, 21 July 2006</timestamp><title>Mike Logan (American football)</title><comment/></version><version><id>65093389</id><timestamp>20:28, 21 July 2006</timestamp><title>Sean Burnett</title><comment/></version><version><id>65092619</id><timestamp>20:24, 21 July 2006</timestamp><title>Pittsburgh Pirates</title><comment/></version><version><id>64937175</id><timestamp>22:55, 20 July 2006</timestamp><title>Who Let the Dogs Out (song)</title><comment/></version><version><id>64738277</id><timestamp>21:46, 19 July 2006</timestamp><title>Demolition Man (film)</title><comment/></version><version><id>64716975</id><timestamp>19:36, 19 July 2006</timestamp><title>The Truman Show</title><comment/></version><version><id>64017298</id><timestamp>21:41, 15 July 2006</timestamp><title>PTI</title><comment/></version><version><id>64016436</id><timestamp>21:34, 15 July 2006</timestamp><title>Abigail Williams</title><comment/></version><version><id>63177692</id><timestamp>05:34, 11 July 2006</timestamp><title>Confederate States of America</title><comment/></version><version><id>63177641</id><timestamp>05:34, 11 July 2006</timestamp><title>Confederate States of America</title><comment/></version></versions>


Chiefmagoo: Subpages
User rights
Edit count
Edit summary search
Articles created
Global: contributions
log
accounts(meta)


Retrieved from "https://en.wikipedia.org/wiki/Special:Contributions"
		
	


	



	Navigation menu
	
		

	
		Personal tools
	
	
	
		
		Not logged inTalkContributionsCreate accountLog in
		
	


		
			

	
		Namespaces
	
	
	
		
		Special page
		
	


			

	
	
		Variants
	
	
	
		
		
		
	


		
		
			

	
		Views
	
	
	
		
		
		
	


			

	
	
		More
	
	
	
		
		
		
	


			
	
		Search
	
	
		
			
			
			
			
		
	


		
	
	

	
		
	
	

	
		Navigation
	
	
	
		
		Main pageContentsCurrent eventsRandom articleAbout WikipediaContact usDonateWikipedia store
		
	


	

	
		Contribute
	
	
	
		
		HelpCommunity portalRecent changesUpload file
		
	



	
		Tools
	
	
	
		
		AtomUser contributionsUser logsView user groupsUpload fileSpecial pagesPrintable version
		
	


	

	
		Languages
	
	
	
		
		
		
	






	
	
	
		Privacy policy
		About Wikipedia
		Disclaimers
		Contact Wikipedia
		Mobile view
		Developers
		Statistics
		Cookie statement
	
	
		
		
	
	



(RLQ=window.RLQ||[]).push(function(){mw.config.set({"wgBackendResponseTime":599,"wgHostname":"mw2305"});});
</user>
