<?xml version="1.0"?>
<user><language>fr</language>


Liste des contributions de l’utilisateur Pigsonthewing — Wikipédia
document.documentElement.className="client-js";RLCONF={"wgBreakFrames":!1,"wgSeparatorTransformTable":[",\t."," \t,"],"wgDigitTransformTable":["",""],"wgDefaultDateFormat":"dmy","wgMonthNames":["","janvier","février","mars","avril","mai","juin","juillet","août","septembre","octobre","novembre","décembre"],"wgRequestId":"XqvpogpAIEIAAGJGWMoAAAAT","wgCSPNonce":!1,"wgCanonicalNamespace":"Special","wgCanonicalSpecialPageName":"Contributions","wgNamespaceNumber":-1,"wgPageName":"Spécial:Contributions","wgTitle":"Contributions","wgCurRevisionId":0,"wgRevisionId":0,"wgArticleId":0,"wgIsArticle":!1,"wgIsRedirect":!1,"wgAction":"view","wgUserName":null,"wgUserGroups":["*"],"wgCategories":[],"wgPageContentLanguage":"fr","wgPageContentModel":"wikitext","wgRelevantPageName":"Spécial:Contributions","wgRelevantArticleId":0,"wgIsProbablyEditable":!1,"wgRelevantPageIsProbablyEditable":!1,"wgRelevantUserName":"Pigsonthewing","wgMediaViewerOnClick":!0,
"wgMediaViewerEnabledByDefault":!0,"wgPopupsReferencePreviews":!1,"wgPopupsConflictsWithNavPopupGadget":!1,"wgVisualEditor":{"pageLanguageCode":"fr","pageLanguageDir":"ltr","pageVariantFallbacks":"fr"},"wgMFDisplayWikibaseDescriptions":{"search":!0,"nearby":!0,"watchlist":!0,"tagline":!0},"wgWMESchemaEditAttemptStepOversample":!1,"wgULSCurrentAutonym":"français","wgNoticeProject":"wikipedia","wgCentralAuthMobileDomain":!1,"wgEditSubmitButtonLabelPublish":!0,"oresData":{"169753865":{"damaging":0.286},"169228086":{"damaging":0.256}},"oresThresholds":{"damaging":{"verylikelybad":0.851,"maybebad":0.083,"likelybad":0.788}}};RLSTATE={"ext.globalCssJs.user.styles":"ready","site.styles":"ready","noscript":"ready","user.styles":"ready","ext.globalCssJs.user":"ready","user":"ready","user.options":"loading","jquery.makeCollapsible.styles":"ready","mediawiki.interface.helpers.styles":"ready","mediawiki.special":"ready","mediawiki.special.changeslist":"ready",
"mediawiki.helplink":"ready","mediawiki.widgets.DateInputWidget.styles":"ready","oojs-ui-core.styles":"ready","oojs-ui.styles.indicators":"ready","mediawiki.widgets.styles":"ready","oojs-ui-core.icons":"ready","mediawiki.htmlform.ooui.styles":"ready","mediawiki.htmlform.styles":"ready","mediawiki.feedlink":"ready","skins.vector.styles.legacy":"ready","ext.visualEditor.desktopArticleTarget.noscript":"ready","ext.uls.interlanguage":"ready","ext.wikimediaBadges":"ready","ext.ores.styles":"ready"};RLPAGEMODULES=["mediawiki.special.recentchanges","mediawiki.page.ready","mediawiki.special.contributions","mediawiki.htmlform","mediawiki.htmlform.ooui","mediawiki.widgets.UserInputWidget","mediawiki.widgets","oojs-ui-widgets","mediawiki.widgets.DateInputWidget","site","mediawiki.page.startup","skins.vector.js","jquery.makeCollapsible","ext.gadget.ArchiveLinks","ext.gadget.MonobookToolbarStandard","ext.gadget.Wdsearch","ext.centralauth.centralautologin","mmv.head","mmv.bootstrap.autostart",
"ext.popups","ext.visualEditor.desktopArticleTarget.init","ext.visualEditor.targetLoader","ext.eventLogging","ext.wikimediaEvents","ext.navigationTiming","ext.uls.compactlinks","ext.uls.interface","ext.cx.eventlogging.campaigns","ext.centralNotice.geoIP"];
(RLQ=window.RLQ||[]).push(function(){mw.loader.implement("user.options@1hzgi",function($,jQuery,require,module){/*@nomin*/mw.user.tokens.set({"patrolToken":"+\\","watchToken":"+\\","csrfToken":"+\\"});mw.user.options.set({"variant":"fr"});
});});
















<name>Pigsonthewing</name>







	
		
	
Aide


	Contributions de l’utilisateur
	
	
		
		Pour Pigsonthewing discuter journal des blocages téléversements journaux journal des filtrages
		
		
		
		Sauter à la navigation
		Sauter à la recherche
		Rechercher des contributionsaffichermasquer⧼contribs-top⧽Adresse IP ou nom d’utilisateur :Espace de noms :Tous(Principal)DiscussionUtilisateurDiscussion utilisateurWikipédiaDiscussion WikipédiaFichierDiscussion fichierMediaWikiDiscussion MediaWikiModèleDiscussion modèleAideDiscussion aideCatégorieDiscussion catégoriePortailDiscussion PortailProjetDiscussion ProjetRéférenceDiscussion RéférenceModuleDiscussion moduleGadgetDiscussion gadgetDéfinition de gadgetDiscussion définition de gadgetSujetInverser la sélectionEspace de noms associéFiltrer les balises :Ne montrer que les contributions qui sont les dernières des articlesAfficher uniquement les créations de pageMasquer les modifications mineures⧼contribs-date⧽À partir du :Jusqu’au :
Cacher les modifications probablement bonnes


Rechercher
(les plus récentes | les plus anciennes) Voir (50 plus récentes  |  50 plus anciennes) (20 | 50 | 100 | 250 | 500)<versions><version><id>169753865</id><timestamp/><date>--</date><time>:</time><title>Bretzel</title><comment/></version><version><id>169228086</id><timestamp/><date>--</date><time>:</time><title>Haricot vert</title><comment/></version><version><id>168457985</id><timestamp/><date>--</date><time>:</time><title>Feu d'artifice</title><comment/></version><version><id>167796911</id><timestamp/><date>--</date><time>:</time><title>Pachydactylus atorquatus</title><comment/></version><version><id>167288644</id><timestamp/><date>--</date><time>:</time><title>John Whitelocke</title><comment/></version><version><id>167013471</id><timestamp/><date>--</date><time>:</time><title>Martin-pêcheur d'Europe</title><comment/></version><version><id>166701134</id><timestamp/><date>--</date><time>:</time><title>Discussion:Cathédrale Saint-Michel de Coventry</title><comment/></version><version><id>165985898</id><timestamp/><date>--</date><time>:</time><title>Un chant de Noël</title><comment/></version><version><id>164591992</id><timestamp/><date>--</date><time>:</time><title>Discussion:ORCID</title><comment/></version><version><id>163160073</id><timestamp/><date>--</date><time>:</time><title>Farzana Aslam</title><comment/></version><version><id>162641803</id><timestamp/><date>--</date><time>:</time><title>Worcester Pearmain</title><comment/></version><version><id>162622048</id><timestamp/><date>--</date><time>:</time><title>Radiodiffusion télévision sénégalaise</title><comment/></version><version><id>162621426</id><timestamp/><date>--</date><time>:</time><title>Inondations de Florence de 1966</title><comment/></version><version><id>162621118</id><timestamp/><date>--</date><time>:</time><title>Bibliothèque nationale centrale de Florence</title><comment/></version><version><id>160488754</id><timestamp/><date>--</date><time>:</time><title>Enid Bagnold</title><comment/></version><version><id>160446372</id><timestamp/><date>--</date><time>:</time><title>John Clerk of Eldin</title><comment/></version><version><id>158402432</id><timestamp/><date>--</date><time>:</time><title>Zeno Payne Metcalf</title><comment/></version><version><id>158152608</id><timestamp/><date>--</date><time>:</time><title>Laurence Housman</title><comment/></version><version><id>157955346</id><timestamp/><date>--</date><time>:</time><title>Amy C. Driskell</title><comment/></version><version><id>157955338</id><timestamp/><date>--</date><time>:</time><title>Certhionyx</title><comment/></version><version><id>157955331</id><timestamp/><date>--</date><time>:</time><title>Certhionyx</title><comment/></version><version><id>157368245</id><timestamp/><date>--</date><time>:</time><title>Swaledale (race ovine)</title><comment/></version><version><id>157367663</id><timestamp/><date>--</date><time>:</time><title>PSR B1919+21</title><comment/></version><version><id>157364739</id><timestamp/><date>--</date><time>:</time><title>Myoglobine</title><comment/></version><version><id>157360931</id><timestamp/><date>--</date><time>:</time><title>LGM-1</title><comment/></version><version><id>157360901</id><timestamp/><date>--</date><time>:</time><title>Jocelyn Bell</title><comment/></version><version><id>157360297</id><timestamp/><date>--</date><time>:</time><title>Pulsar</title><comment/></version><version><id>157344413</id><timestamp/><date>--</date><time>:</time><title>Caroline Criado-Perez</title><comment/></version><version><id>157069332</id><timestamp/><date>--</date><time>:</time><title>Codsall</title><comment/></version><version><id>156467368</id><timestamp/><date>--</date><time>:</time><title>Modèle:ARKive</title><comment/></version><version><id>156466950</id><timestamp/><date>--</date><time>:</time><title>Modèle:ARKive</title><comment/></version><version><id>156177495</id><timestamp/><date>--</date><time>:</time><title>Matthew Flinders</title><comment/></version><version><id>156177440</id><timestamp/><date>--</date><time>:</time><title>Antoine Toussaint de Chazal</title><comment/></version><version><id>154541951</id><timestamp/><date>--</date><time>:</time><title>Boîte à thé</title><comment/></version><version><id>154459096</id><timestamp/><date>--</date><time>:</time><title>Ren Hirayama</title><comment/></version><version><id>153350506</id><timestamp/><date>--</date><time>:</time><title>William Warde Fowler</title><comment/></version><version><id>151748879</id><timestamp/><date>--</date><time>:</time><title>Extraction dentaire</title><comment/></version><version><id>150895580</id><timestamp/><date>--</date><time>:</time><title>Sparodon durbanensis</title><comment/></version><version><id>150895416</id><timestamp/><date>--</date><time>:</time><title>Sparodon durbanensis</title><comment/></version><version><id>150691908</id><timestamp/><date>--</date><time>:</time><title>Sparodon durbanensis</title><comment/></version><version><id>150295690</id><timestamp/><date>--</date><time>:</time><title>Pierre Prévost (peintre)</title><comment/></version><version><id>150295636</id><timestamp/><date>--</date><time>:</time><title>Pierre Prévost (peintre)</title><comment/></version><version><id>150295630</id><timestamp/><date>--</date><time>:</time><title>Pierre Prévost (peintre)</title><comment/></version><version><id>149584040</id><timestamp/><date>--</date><time>:</time><title>Auguste Michel-Lévy</title><comment/></version><version><id>148803092</id><timestamp/><date>--</date><time>:</time><title>Alexander L. Wolf</title><comment/></version><version><id>147752819</id><timestamp/><date>--</date><time>:</time><title>Édouard Ngirente</title><comment/></version><version><id>147752776</id><timestamp/><date>--</date><time>:</time><title>Édouard Ngirente</title><comment/></version><version><id>146792679</id><timestamp/><date>--</date><time>:</time><title>Norman Tebbit</title><comment/></version><version><id>146559821</id><timestamp/><date>--</date><time>:</time><title>The Book of Gabrielle</title><comment/></version><version><id>145972984</id><timestamp/><date>--</date><time>:</time><title>Franco Andreone</title><comment/></version></versions>
(les plus récentes | les plus anciennes) Voir (50 plus récentes  |  50 plus anciennes) (20 | 50 | 100 | 250 | 500)




Outils :
Sous-pages
Wikiscan, XTools
Articles créés
Fichiers importés (Commons)
Contributions sur les autres projets
Compte global



		Ce document provient de « https://fr.wikipedia.org/wiki/Spécial:Contributions ».
		
		
		
	


	



	Menu de navigation
	
		

	Outils personnels
	
		Non connectéDiscussionContributionsCréer un compteSe connecter
	


		
			
	Espaces de noms
	
		Page spéciale
	


			
	
	
		Variantes
	
	
		
	


		
		
			
	Affichages
	
		
	


			
	
	
		Plus
	
	
		
	


			
	
		Rechercher
	
	
		
			
			
			
			
		
	


		
	
	

	
		
	
	
	
		Navigation
	
	
		AccueilPortails thématiquesArticle au hasardContact
		
	



	
	
		Contribuer
	
	
		Débuter sur WikipédiaAideCommunautéModifications récentesFaire un don
		
	



	
		Outils
	
	
		AtomContributions de l’utilisateurJournaux d’opérationsVoir les groupes de l’utilisateurTéléverser un fichierPages spécialesVersion imprimable
		
	



	
		Dans d’autres langues
	
	
		
		
	








	
		Politique de confidentialité
		À propos de Wikipédia
		Avertissements
		Contact
		Développeurs
		Statistiques
		Déclaration sur les témoins (cookies)
		Version mobile
	
	
		
		
	
	



(RLQ=window.RLQ||[]).push(function(){mw.config.set({"wgBackendResponseTime":330,"wgHostname":"mw1329"});});</user>
