<?xml version="1.0"?>
<user><language>zh</language>


Whhalbert的用户贡献 - 维基百科，自由的百科全书
document.documentElement.className="client-js";RLCONF={"wgBreakFrames":!1,"wgSeparatorTransformTable":["",""],"wgDigitTransformTable":["",""],"wgDefaultDateFormat":"zh","wgMonthNames":["","1月","2月","3月","4月","5月","6月","7月","8月","9月","10月","11月","12月"],"wgRequestId":"bb0ccaf3-3cd0-4e1b-87d0-24971b3f9bfe","wgCSPNonce":!1,"wgCanonicalNamespace":"Special","wgCanonicalSpecialPageName":"Contributions","wgNamespaceNumber":-1,"wgPageName":"Special:用户贡献","wgTitle":"用户贡献","wgCurRevisionId":0,"wgRevisionId":0,"wgArticleId":0,"wgIsArticle":!1,"wgIsRedirect":!1,"wgAction":"view","wgUserName":null,"wgUserGroups":["*"],"wgCategories":[],"wgPageContentLanguage":"zh","wgPageContentModel":"wikitext","wgRelevantPageName":"Special:用户贡献","wgRelevantArticleId":0,"wgUserVariant":"zh","wgIsProbablyEditable":!1,"wgRelevantPageIsProbablyEditable":!1,"wgRelevantUserName":"Whhalbert","wgMediaViewerOnClick":!0,"wgMediaViewerEnabledByDefault":!0,
"wgPopupsReferencePreviews":!1,"wgPopupsConflictsWithNavPopupGadget":!1,"wgVisualEditor":{"pageLanguageCode":"zh","pageLanguageDir":"ltr","pageVariantFallbacks":["zh-hans","zh-hant","zh-cn","zh-tw","zh-hk","zh-sg","zh-mo","zh-my"]},"wgMFDisplayWikibaseDescriptions":{"search":!0,"nearby":!0,"watchlist":!0,"tagline":!0},"wgWMESchemaEditAttemptStepOversample":!1,"wgULSCurrentAutonym":"中文","wgNoticeProject":"wikipedia","wgCentralAuthMobileDomain":!1,"wgEditSubmitButtonLabelPublish":!0,"wgULSPosition":"interlanguage"};RLSTATE={"ext.gadget.hideConversionTab":"ready","ext.gadget.large-font":"ready","ext.globalCssJs.user.styles":"ready","site.styles":"ready","noscript":"ready","user.styles":"ready","ext.globalCssJs.user":"ready","user":"ready","user.options":"loading","jquery.makeCollapsible.styles":"ready","mediawiki.interface.helpers.styles":"ready","mediawiki.special":"ready","mediawiki.special.changeslist":"ready","mediawiki.helplink":"ready",
"mediawiki.widgets.DateInputWidget.styles":"ready","oojs-ui-core.styles":"ready","oojs-ui.styles.indicators":"ready","mediawiki.widgets.styles":"ready","oojs-ui-core.icons":"ready","mediawiki.htmlform.ooui.styles":"ready","mediawiki.htmlform.styles":"ready","skins.vector.styles.legacy":"ready","mediawiki.feedlink":"ready","ext.visualEditor.desktopArticleTarget.noscript":"ready","ext.uls.interlanguage":"ready","ext.wikimediaBadges":"ready"};RLPAGEMODULES=["mediawiki.special.recentchanges","mediawiki.page.ready","mediawiki.special.contributions","mediawiki.htmlform","mediawiki.htmlform.ooui","mediawiki.widgets.UserInputWidget","mediawiki.widgets","oojs-ui-widgets","mediawiki.widgets.DateInputWidget","site","jquery.makeCollapsible","skins.vector.legacy.js","ext.gadget.edit0","ext.gadget.Edittools-refToolbar","ext.gadget.WikiMiniAtlas","ext.gadget.ReferenceTooltips","ext.gadget.UnihanTooltips","ext.gadget.variant-link-fix","ext.gadget.FixedTopBottomLink","ext.gadget.confirm-logout",
"ext.gadget.shortURL","ext.gadget.AdvancedSiteNotices","ext.gadget.internalLinkHelper-altcolor","ext.gadget.noteTA","ext.gadget.noteTAvector","ext.gadget.NavFrame","ext.gadget.collapsibleTables","ext.gadget.notifyConversion","ext.centralauth.centralautologin","mmv.head","mmv.bootstrap.autostart","ext.popups","ext.visualEditor.desktopArticleTarget.init","ext.visualEditor.targetLoader","ext.eventLogging","ext.wikimediaEvents","ext.navigationTiming","ext.uls.compactlinks","ext.uls.interface","ext.cx.eventlogging.campaigns","ext.centralNotice.geoIP"];
(RLQ=window.RLQ||[]).push(function(){mw.loader.implement("user.options@1hzgi",function($,jQuery,require,module){/*@nomin*/mw.user.tokens.set({"patrolToken":"+\\","watchToken":"+\\","csrfToken":"+\\"});
});});



























<name>Whhalbert</name>





	
	
	
	帮助
	
	用户贡献
	
		
		Whhalbert 讨论 封禁日志 上传 日志 过滤器日志
		
		
		
		跳到导航
		跳到搜索
		搜索贡献记录展开折叠⧼contribs-top⧽IP地址或用户名：名字空间：所有条目TalkUserUser talk维基百科维基百科讨论FileFile talkMediaWikiMediaWiki talkTemplateTemplate talkHelpHelp talkCategoryCategory talk主题主题讨论草稿草稿讨论模組模組討論GadgetGadget talkGadget definitionGadget definition talkTopic反向选择关联的名字空间标签过滤器：仅显示最后版本的编辑仅显示创建页面的编辑隐藏小编辑⧼contribs-date⧽起始日：截止日：
隐藏可能良好编辑


搜索
（最近 | 最旧） 查看（前500个 | 后500个）（20 | 50 | 100 | 250 | 500）<versions><version><id>33128687</id><timestamp>2014年10月30日 (四) 15:32</timestamp><title>赛伯伊人</title><comment/></version><version><id>33119971</id><timestamp>2014年10月29日 (三) 18:09</timestamp><title>宗座憲令</title><comment/></version><version><id>33119948</id><timestamp>2014年10月29日 (三) 18:04</timestamp><title>宗座憲令</title><comment/></version><version><id>33119947</id><timestamp>2014年10月29日 (三) 18:04</timestamp><title>宗座憲令</title><comment/></version><version><id>33119944</id><timestamp>2014年10月29日 (三) 18:02</timestamp><title>宗座憲令</title><comment/></version><version><id>33119246</id><timestamp>2014年10月29日 (三) 16:01</timestamp><title>天主教索拉-卡西諾-阿奎諾-蓬泰科爾沃教區</title><comment/></version><version><id>33119238</id><timestamp>2014年10月29日 (三) 16:01</timestamp><title>意大利天主教教区列表</title><comment/></version><version><id>33119233</id><timestamp>2014年10月29日 (三) 16:00</timestamp><title>Template:意大利天主教教區</title><comment/></version><version><id>33119223</id><timestamp/><title>天主教索拉-阿奎諾-蓬泰科爾沃教區</title><comment/></version><version><id>33119222</id><timestamp>2014年10月29日 (三) 15:59</timestamp><title>天主教索拉-卡西諾-阿奎諾-蓬泰科爾沃教區</title><comment/></version><version><id>33119218</id><timestamp>2014年10月29日 (三) 15:58</timestamp><title>天主教索拉-卡西諾-阿奎諾-蓬泰科爾沃教區</title><comment/></version><version><id>33119203</id><timestamp>2014年10月29日 (三) 15:57</timestamp><title>天主教卡西諾山自治會院區</title><comment/></version><version><id>33119177</id><timestamp>2014年10月29日 (三) 15:54</timestamp><title>天主教卡西諾山自治會院區</title><comment/></version><version><id>33119171</id><timestamp>2014年10月29日 (三) 15:53</timestamp><title>天主教卡西諾山自治會院區</title><comment/></version><version><id>33093650</id><timestamp>2014年10月27日 (一) 06:27</timestamp><title>User:Whhalbert/Sandbox 11</title><comment/></version><version><id>33093593</id><timestamp>2014年10月27日 (一) 06:17</timestamp><title>天主教諾瓦拉教區</title><comment/></version><version><id>33093587</id><timestamp>2014年10月27日 (一) 06:16</timestamp><title>天主教諾瓦拉教區</title><comment/></version><version><id>33093584</id><timestamp>2014年10月27日 (一) 06:15</timestamp><title>天主教諾瓦拉教區</title><comment/></version><version><id>33093397</id><timestamp>2014年10月27日 (一) 05:51</timestamp><title>天主教諾瓦拉教區</title><comment/></version><version><id>33093394</id><timestamp>2014年10月27日 (一) 05:50</timestamp><title>天主教諾瓦拉教區</title><comment/></version><version><id>33092773</id><timestamp>2014年10月27日 (一) 04:36</timestamp><title>天主教比耶拉教區</title><comment/></version><version><id>33092683</id><timestamp>2014年10月27日 (一) 04:23</timestamp><title>天主教亞歷山德里亞教區 (義大利)</title><comment/></version><version><id>33092579</id><timestamp>2014年10月27日 (一) 04:11</timestamp><title>天主教貝加莫教區</title><comment/></version><version><id>33092576</id><timestamp>2014年10月27日 (一) 04:10</timestamp><title>天主教貝加莫教區</title><comment/></version><version><id>33080607</id><timestamp>2014年10月26日 (日) 01:47</timestamp><title>櫻田門事件</title><comment/></version><version><id>33059168</id><timestamp>2014年10月23日 (四) 17:31</timestamp><title>天主教維傑瓦諾教區</title><comment/></version><version><id>33059152</id><timestamp>2014年10月23日 (四) 17:28</timestamp><title>天主教維傑瓦諾教區</title><comment/></version><version><id>33058732</id><timestamp>2014年10月23日 (四) 16:22</timestamp><title>天主教帕維亞教區</title><comment/></version><version><id>33058723</id><timestamp>2014年10月23日 (四) 16:21</timestamp><title>天主教帕維亞教區</title><comment/></version><version><id>32972420</id><timestamp>2014年10月14日 (二) 15:55</timestamp><title>Wikipedia:新条目推荐/候选</title><comment/></version><version><id>32966162</id><timestamp>2014年10月14日 (二) 03:21</timestamp><title>天主教尼亞美總教區</title><comment/></version><version><id>32956906</id><timestamp>2014年10月13日 (一) 06:26</timestamp><title>天主教曼托瓦教區</title><comment/></version><version><id>32956445</id><timestamp>2014年10月13日 (一) 05:34</timestamp><title>Category:兰州政治</title><comment/></version><version><id>32956443</id><timestamp>2014年10月13日 (一) 05:34</timestamp><title>热冬果</title><comment/></version><version><id>32956436</id><timestamp>2014年10月13日 (一) 05:33</timestamp><title>热冬果</title><comment/></version><version><id>32956309</id><timestamp>2014年10月13日 (一) 05:22</timestamp><title>天主教洛迪教區</title><comment/></version><version><id>32956264</id><timestamp>2014年10月13日 (一) 05:16</timestamp><title>天主教洛迪教區</title><comment/></version><version><id>32956138</id><timestamp>2014年10月13日 (一) 04:59</timestamp><title>天主教洛迪教區</title><comment/></version><version><id>32956136</id><timestamp>2014年10月13日 (一) 04:58</timestamp><title>天主教洛迪教區</title><comment/></version><version><id>32956133</id><timestamp>2014年10月13日 (一) 04:57</timestamp><title>天主教洛迪教區</title><comment/></version><version><id>32956117</id><timestamp>2014年10月13日 (一) 04:56</timestamp><title>天主教洛迪教區</title><comment/></version><version><id>32955892</id><timestamp>2014年10月13日 (一) 04:27</timestamp><title>天主教克雷馬教區</title><comment/></version><version><id>32955817</id><timestamp>2014年10月13日 (一) 04:16</timestamp><title>天主教克雷莫納教區</title><comment/></version><version><id>32955797</id><timestamp>2014年10月13日 (一) 04:12</timestamp><title>天主教克雷莫納教區</title><comment/></version><version><id>32955745</id><timestamp>2014年10月13日 (一) 04:06</timestamp><title>天主教克雷莫納教區</title><comment/></version><version><id>32955738</id><timestamp>2014年10月13日 (一) 04:05</timestamp><title>天主教克雷莫納教區</title><comment/></version><version><id>32955711</id><timestamp>2014年10月13日 (一) 04:00</timestamp><title>天主教克雷莫納教區</title><comment/></version><version><id>32955703</id><timestamp>2014年10月13日 (一) 03:59</timestamp><title>天主教克雷莫納教區</title><comment/></version><version><id>32955696</id><timestamp>2014年10月13日 (一) 03:58</timestamp><title>天主教克雷莫納教區</title><comment/></version><version><id>32955256</id><timestamp>2014年10月13日 (一) 03:14</timestamp><title>天主教布雷西亞教區</title><comment/></version><version><id>32954992</id><timestamp>2014年10月13日 (一) 02:37</timestamp><title>天主教科莫教區</title><comment/></version><version><id>32944591</id><timestamp>2014年10月12日 (日) 03:33</timestamp><title>李志超 (攝影家)</title><comment/></version><version><id>32944057</id><timestamp>2014年10月12日 (日) 02:30</timestamp><title>李志超 (攝影家)</title><comment/></version><version><id>32944033</id><timestamp>2014年10月12日 (日) 02:27</timestamp><title>李志超 (攝影家)</title><comment/></version><version><id>32943952</id><timestamp>2014年10月12日 (日) 02:17</timestamp><title>李志超 (攝影家)</title><comment/></version><version><id>32943940</id><timestamp>2014年10月12日 (日) 02:15</timestamp><title>李志超 (攝影家)</title><comment/></version><version><id>32943933</id><timestamp>2014年10月12日 (日) 02:14</timestamp><title>李志超 (攝影家)</title><comment/></version><version><id>32943198</id><timestamp>2014年10月12日 (日) 00:28</timestamp><title>理查德·瓦格纳</title><comment/></version><version><id>32943185</id><timestamp>2014年10月12日 (日) 00:27</timestamp><title>古斯塔夫·馬勒</title><comment/></version><version><id>32933852</id><timestamp>2014年10月11日 (六) 03:06</timestamp><title>天主教巴拿馬城總教區</title><comment/></version><version><id>32933847</id><timestamp>2014年10月11日 (六) 03:06</timestamp><title>天主教巴拿馬城總教區</title><comment/></version><version><id>32933802</id><timestamp>2014年10月11日 (六) 02:59</timestamp><title>Template:愛爾蘭行政區劃</title><comment/></version><version><id>32933795</id><timestamp>2014年10月11日 (六) 02:58</timestamp><title>南蒂珀雷里郡</title><comment/></version><version><id>32933792</id><timestamp>2014年10月11日 (六) 02:58</timestamp><title>北蒂珀雷里郡</title><comment/></version><version><id>32933772</id><timestamp>2014年10月11日 (六) 02:55</timestamp><title>愛爾蘭行政區劃</title><comment/></version><version><id>32933756</id><timestamp>2014年10月11日 (六) 02:54</timestamp><title>愛爾蘭行政區劃</title><comment/></version><version><id>32933744</id><timestamp>2014年10月11日 (六) 02:53</timestamp><title>沃特福德 (芒斯特省)</title><comment/></version><version><id>32933736</id><timestamp>2014年10月11日 (六) 02:52</timestamp><title>沃特福德 (芒斯特省)</title><comment/></version><version><id>32933726</id><timestamp>2014年10月11日 (六) 02:51</timestamp><title>沃特福德郡</title><comment/></version><version><id>32933613</id><timestamp>2014年10月11日 (六) 02:41</timestamp><title>Template:愛爾蘭行政區劃</title><comment/></version><version><id>32933611</id><timestamp>2014年10月11日 (六) 02:40</timestamp><title>Template:愛爾蘭行政區劃</title><comment/></version><version><id>32933603</id><timestamp>2014年10月11日 (六) 02:40</timestamp><title>蒂珀雷里郡</title><comment/></version><version><id>32933592</id><timestamp>2014年10月11日 (六) 02:39</timestamp><title>愛爾蘭行政區劃</title><comment/></version><version><id>32933555</id><timestamp/><title>赛宋本行政特区</title><comment/></version><version><id>32933554</id><timestamp>2014年10月11日 (六) 02:36</timestamp><title>賽宋奔省</title><comment/></version><version><id>32933550</id><timestamp>2014年10月11日 (六) 02:35</timestamp><title>賽宋奔省</title><comment/></version><version><id>32933503</id><timestamp>2014年10月11日 (六) 02:30</timestamp><title>巴拿馬省</title><comment/></version><version><id>32933476</id><timestamp>2014年10月11日 (六) 02:27</timestamp><title>西巴拿馬省</title><comment/></version><version><id>32933467</id><timestamp>2014年10月11日 (六) 02:26</timestamp><title>西巴拿馬省</title><comment/></version><version><id>32933463</id><timestamp>2014年10月11日 (六) 02:26</timestamp><title>西巴拿馬省</title><comment/></version><version><id>32933437</id><timestamp>2014年10月11日 (六) 02:22</timestamp><title>巴拿馬省</title><comment/></version><version><id>32933411</id><timestamp>2014年10月11日 (六) 02:19</timestamp><title>Template:巴拿馬行政區劃</title><comment/></version><version><id>32933403</id><timestamp>2014年10月11日 (六) 02:18</timestamp><title>巴拿馬省</title><comment/></version><version><id>32933215</id><timestamp>2014年10月11日 (六) 01:52</timestamp><title>天主教阿爾塔穆拉-格拉維納-阿夸維瓦德萊豐蒂教區</title><comment/></version><version><id>32933130</id><timestamp>2014年10月11日 (六) 01:36</timestamp><title>天主教菲登扎教區</title><comment/></version><version><id>32929561</id><timestamp>2014年10月10日 (五) 14:00</timestamp><title>Template:意大利天主教教區</title><comment/></version><version><id>32929530</id><timestamp>2014年10月10日 (五) 13:58</timestamp><title>天主教阿爾塔穆拉-格拉維納-阿夸維瓦德萊豐蒂教區</title><comment/></version><version><id>32929509</id><timestamp>2014年10月10日 (五) 13:57</timestamp><title>天主教阿爾塔穆拉-格拉維納-阿夸維瓦德萊豐蒂教區</title><comment/></version><version><id>32929170</id><timestamp/><title>桑托斯將軍城</title><comment/></version><version><id>32929104</id><timestamp>2014年10月10日 (五) 13:19</timestamp><title>User:Whhalbert/Sandbox 11</title><comment/></version><version><id>32927468</id><timestamp>2014年10月10日 (五) 09:54</timestamp><title>User:Whhalbert/Sandbox 11</title><comment/></version><version><id>32923610</id><timestamp>2014年10月10日 (五) 01:54</timestamp><title>克拉克頓 (英國國會選區)</title><comment/></version><version><id>32923602</id><timestamp>2014年10月10日 (五) 01:53</timestamp><title>2014年10月</title><comment/></version><version><id>32914757</id><timestamp>2014年10月9日 (四) 01:47</timestamp><title>蘇嘉豪</title><comment/></version><version><id>32912510</id><timestamp>2014年10月8日 (三) 17:11</timestamp><title>意大利天主教教区列表</title><comment/></version><version><id>32912505</id><timestamp>2014年10月8日 (三) 17:10</timestamp><title>Template:意大利天主教教區</title><comment/></version><version><id>32912497</id><timestamp/><title>天主教莫爾費塔-魯沃迪普利亞-焦維納佐-泰爾利齊教區</title><comment/></version><version><id>32912496</id><timestamp>2014年10月8日 (三) 17:09</timestamp><title>天主教莫爾費塔-魯沃-焦維納佐-泰爾利齊教區</title><comment/></version><version><id>32912492</id><timestamp>2014年10月8日 (三) 17:09</timestamp><title>天主教莫爾費塔-魯沃-焦維納佐-泰爾利齊教區</title><comment/></version><version><id>32912444</id><timestamp>2014年10月8日 (三) 17:01</timestamp><title>天主教莫爾費塔-魯沃-焦維納佐-泰爾利齊教區</title><comment/></version><version><id>32903671</id><timestamp>2014年10月8日 (三) 00:40</timestamp><title>天主教孔韋爾薩諾-莫諾波利教區</title><comment/></version><version><id>32903659</id><timestamp>2014年10月8日 (三) 00:39</timestamp><title>天主教孔韋爾薩諾-莫諾波利教區</title><comment/></version><version><id>32903654</id><timestamp>2014年10月8日 (三) 00:37</timestamp><title>天主教孔韋爾薩諾-莫諾波利教區</title><comment/></version><version><id>32903651</id><timestamp>2014年10月8日 (三) 00:37</timestamp><title>天主教孔韋爾薩諾-莫諾波利教區</title><comment/></version><version><id>32903642</id><timestamp>2014年10月8日 (三) 00:36</timestamp><title>天主教孔韋爾薩諾-莫諾波利教區</title><comment/></version><version><id>32903546</id><timestamp>2014年10月8日 (三) 00:02</timestamp><title>User:Whhalbert/Sandbox 11</title><comment/></version><version><id>32903525</id><timestamp>2014年10月7日 (二) 23:55</timestamp><title>天主教文蒂米利亞-聖雷莫教區</title><comment/></version><version><id>32903522</id><timestamp>2014年10月7日 (二) 23:54</timestamp><title>天主教文蒂米利亞-聖雷莫教區</title><comment/></version><version><id>32903516</id><timestamp>2014年10月7日 (二) 23:52</timestamp><title>天主教文蒂米利亞-聖雷莫教區</title><comment/></version><version><id>32901470</id><timestamp>2014年10月7日 (二) 14:52</timestamp><title>匹兹堡国际机场</title><comment/></version><version><id>32901461</id><timestamp>2014年10月7日 (二) 14:51</timestamp><title>普里鄂毕油田</title><comment/></version><version><id>32901452</id><timestamp>2014年10月7日 (二) 14:50</timestamp><title>俄罗斯石油</title><comment/></version><version><id>32901451</id><timestamp>2014年10月7日 (二) 14:50</timestamp><title>砂拉越博物馆</title><comment/></version><version><id>32901436</id><timestamp>2014年10月7日 (二) 14:49</timestamp><title>俄罗斯石油</title><comment/></version><version><id>32901424</id><timestamp/><title>萨宗诺夫</title><comment/></version><version><id>32901423</id><timestamp>2014年10月7日 (二) 14:48</timestamp><title>謝爾蓋·薩宗諾夫</title><comment/></version><version><id>32901422</id><timestamp>2014年10月7日 (二) 14:48</timestamp><title>謝爾蓋·薩宗諾夫</title><comment/></version><version><id>32901415</id><timestamp/><title>帕希奇</title><comment/></version><version><id>32901414</id><timestamp>2014年10月7日 (二) 14:47</timestamp><title>尼古拉·帕希奇</title><comment/></version><version><id>32898791</id><timestamp>2014年10月7日 (二) 09:58</timestamp><title>User:Whhalbert/Sandbox 11</title><comment/></version><version><id>32898625</id><timestamp>2014年10月7日 (二) 09:39</timestamp><title>意大利天主教教区列表</title><comment/></version><version><id>32898316</id><timestamp>2014年10月7日 (二) 09:08</timestamp><title>天主教安德里亚教区</title><comment/></version><version><id>32898043</id><timestamp>2014年10月7日 (二) 08:40</timestamp><title>天主教科莫教區</title><comment/></version><version><id>32897947</id><timestamp>2014年10月7日 (二) 08:27</timestamp><title>廖炳堅</title><comment/></version><version><id>32897683</id><timestamp>2014年10月7日 (二) 07:54</timestamp><title>天主教基亞瓦里教區</title><comment/></version><version><id>32897656</id><timestamp>2014年10月7日 (二) 07:50</timestamp><title>天主教基亞瓦里教區</title><comment/></version><version><id>32897510</id><timestamp>2014年10月7日 (二) 07:35</timestamp><title>User:Whhalbert/Sandbox 11</title><comment/></version><version><id>32897155</id><timestamp>2014年10月7日 (二) 06:59</timestamp><title>天主教托爾托納教區</title><comment/></version><version><id>32894758</id><timestamp/><title>阿塞拜疆天主教教区列表</title><comment/></version><version><id>32894746</id><timestamp/><title>亚美尼亚天主教教区列表</title><comment/></version><version><id>32894745</id><timestamp/><title>格鲁吉亚天主教教区列表</title><comment/></version><version><id>32894592</id><timestamp>2014年10月7日 (二) 02:08</timestamp><title>天主教阿爾本加-因佩里亞教區</title><comment/></version><version><id>32891041</id><timestamp>2014年10月6日 (一) 15:16</timestamp><title>Wikipedia:互助客栈/方针</title><comment/></version><version><id>32887010</id><timestamp>2014年10月6日 (一) 09:37</timestamp><title>天主教阿爾本加-因佩里亞教區</title><comment/></version><version><id>32887009</id><timestamp>2014年10月6日 (一) 09:36</timestamp><title>天主教阿爾本加-因佩里亞教區</title><comment/></version><version><id>32887004</id><timestamp>2014年10月6日 (一) 09:36</timestamp><title>意大利天主教教区列表</title><comment/></version><version><id>32886997</id><timestamp>2014年10月6日 (一) 09:35</timestamp><title>天主教阿爾本加-因佩里亞教區</title><comment/></version><version><id>32886990</id><timestamp>2014年10月6日 (一) 09:35</timestamp><title>Template:意大利天主教教區</title><comment/></version><version><id>32886960</id><timestamp>2014年10月6日 (一) 09:31</timestamp><title>天主教阿爾本加-因佩里亞教區</title><comment/></version><version><id>32886950</id><timestamp>2014年10月6日 (一) 09:29</timestamp><title>天主教阿爾本加-因佩里亞教區</title><comment/></version><version><id>32886927</id><timestamp>2014年10月6日 (一) 09:27</timestamp><title>天主教薩沃納-諾利教區</title><comment/></version><version><id>32886273</id><timestamp>2014年10月6日 (一) 08:28</timestamp><title>天主教薩沃納-諾利教區</title><comment/></version><version><id>32885569</id><timestamp>2014年10月6日 (一) 06:57</timestamp><title>天主教薩沃納-諾利教區</title><comment/></version><version><id>32874577</id><timestamp>2014年10月5日 (日) 05:52</timestamp><title>天主教拉斯佩齊亞-薩爾扎納-布魯尼亞托教區</title><comment/></version><version><id>32874573</id><timestamp>2014年10月5日 (日) 05:51</timestamp><title>天主教拉斯佩齊亞-薩爾扎納-布魯尼亞托教區</title><comment/></version><version><id>32869998</id><timestamp>2014年10月4日 (六) 16:32</timestamp><title>天主教雷焦艾米利亞-瓜斯塔拉教區</title><comment/></version><version><id>32868020</id><timestamp>2014年10月4日 (六) 13:01</timestamp><title>天主教菲登扎教區</title><comment/></version><version><id>32868012</id><timestamp>2014年10月4日 (六) 13:01</timestamp><title>天主教菲登扎教區</title><comment/></version><version><id>32858699</id><timestamp>2014年10月3日 (五) 16:40</timestamp><title>天主教雷焦艾米利亞-瓜斯塔拉教區</title><comment/></version><version><id>32844386</id><timestamp>2014年10月2日 (四) 08:03</timestamp><title>聖龐加爵</title><comment/></version><version><id>32827095</id><timestamp>2014年9月30日 (二) 13:09</timestamp><title>Wikipedia:新条目推荐/候选</title><comment/></version><version><id>32811746</id><timestamp>2014年9月29日 (一) 01:55</timestamp><title>聖龐加爵</title><comment/></version><version><id>32792189</id><timestamp>2014年9月26日 (五) 17:44</timestamp><title>天主教埃斯特城教區</title><comment/></version><version><id>32792160</id><timestamp>2014年9月26日 (五) 17:37</timestamp><title>天主教埃斯特城教區</title><comment/></version><version><id>32761843</id><timestamp>2014年9月23日 (二) 09:59</timestamp><title>User:Whhalbert/Sandbox 11</title><comment/></version><version><id>32758425</id><timestamp>2014年9月23日 (二) 02:55</timestamp><title>摩拉維亞</title><comment/></version><version><id>32758004</id><timestamp>2014年9月23日 (二) 01:42</timestamp><title>天主教皮亞琴察-博比奧教區</title><comment/></version><version><id>32758003</id><timestamp>2014年9月23日 (二) 01:42</timestamp><title>天主教皮亞琴察-博比奧教區</title><comment/></version><version><id>32755254</id><timestamp>2014年9月22日 (一) 14:39</timestamp><title>天主教皮亞琴察-博比奧教區</title><comment/></version><version><id>32753009</id><timestamp>2014年9月22日 (一) 10:51</timestamp><title>天主教卡尔皮教区</title><comment/></version><version><id>32752572</id><timestamp>2014年9月22日 (一) 09:58</timestamp><title>天主教奇維塔卡斯泰拉納教區</title><comment/></version><version><id>32752555</id><timestamp>2014年9月22日 (一) 09:56</timestamp><title>天主教奇維塔卡斯泰拉納教區</title><comment/></version><version><id>32752542</id><timestamp>2014年9月22日 (一) 09:54</timestamp><title>天主教奇維塔卡斯泰拉納教區</title><comment/></version><version><id>32751760</id><timestamp>2014年9月22日 (一) 08:25</timestamp><title>天主教蒂沃利教區</title><comment/></version><version><id>32751724</id><timestamp>2014年9月22日 (一) 08:20</timestamp><title>天主教蒂沃利教區</title><comment/></version><version><id>32751243</id><timestamp>2014年9月22日 (一) 07:21</timestamp><title>Talk:豆豉</title><comment/></version><version><id>32751232</id><timestamp>2014年9月22日 (一) 07:19</timestamp><title>天主教列蒂教區</title><comment/></version><version><id>32749888</id><timestamp>2014年9月22日 (一) 03:59</timestamp><title>天主教列蒂教區</title><comment/></version><version><id>32749845</id><timestamp>2014年9月22日 (一) 03:52</timestamp><title>天主教列蒂教區</title><comment/></version><version><id>32748992</id><timestamp>2014年9月22日 (一) 01:36</timestamp><title>天主教阿納尼-阿拉特里教區</title><comment/></version><version><id>32748983</id><timestamp>2014年9月22日 (一) 01:35</timestamp><title>天主教阿納尼-阿拉特里教區</title><comment/></version><version><id>32748909</id><timestamp>2014年9月22日 (一) 01:23</timestamp><title>马尼拉市政厅</title><comment/></version><version><id>32747591</id><timestamp>2014年9月21日 (日) 18:01</timestamp><title>Wikipedia:新条目推荐/候选</title><comment/></version><version><id>32747586</id><timestamp>2014年9月21日 (日) 18:00</timestamp><title>Wikipedia:新条目推荐/候选</title><comment/></version><version><id>32740474</id><timestamp>2014年9月21日 (日) 05:51</timestamp><title>天主教阿納尼-阿拉特里教區</title><comment/></version><version><id>32740451</id><timestamp>2014年9月21日 (日) 05:48</timestamp><title>天主教阿納尼-阿拉特里教區</title><comment/></version><version><id>32739925</id><timestamp>2014年9月21日 (日) 04:56</timestamp><title>天主教索拉-卡西諾-阿奎諾-蓬泰科爾沃教區</title><comment/></version><version><id>32739911</id><timestamp>2014年9月21日 (日) 04:55</timestamp><title>天主教索拉-卡西諾-阿奎諾-蓬泰科爾沃教區</title><comment/></version><version><id>32739559</id><timestamp>2014年9月21日 (日) 04:15</timestamp><title>中毛关系</title><comment/></version><version><id>32739546</id><timestamp>2014年9月21日 (日) 04:13</timestamp><title>美國駐外機構列表</title><comment/></version><version><id>32739523</id><timestamp>2014年9月21日 (日) 04:10</timestamp><title>美國駐外機構列表</title><comment/></version><version><id>32739509</id><timestamp>2014年9月21日 (日) 04:08</timestamp><title>美國駐外機構列表</title><comment/></version><version><id>32739484</id><timestamp>2014年9月21日 (日) 04:07</timestamp><title>美國駐外機構列表</title><comment/></version><version><id>32739462</id><timestamp>2014年9月21日 (日) 04:04</timestamp><title>中毛关系</title><comment/></version><version><id>32739461</id><timestamp>2014年9月21日 (日) 04:04</timestamp><title>中国－毛里求斯关系</title><comment/></version><version><id>32732538</id><timestamp>2014年9月20日 (六) 12:21</timestamp><title>托馬斯·布拉德華</title><comment/></version><version><id>32732429</id><timestamp>2014年9月20日 (六) 12:10</timestamp><title>天主教弗羅西諾內-韋羅利-費倫蒂諾教區</title><comment/></version><version><id>32732174</id><timestamp>2014年9月20日 (六) 11:44</timestamp><title>法蘭克·穆考斯基</title><comment/></version><version><id>32712865</id><timestamp>2014年9月18日 (四) 14:44</timestamp><title>天主教拉蒂纳-泰拉奇纳-塞泽-普里韦尔诺教区</title><comment/></version><version><id>32712620</id><timestamp>2014年9月18日 (四) 14:19</timestamp><title>天主教拉蒂纳-泰拉奇纳-塞泽-普里韦尔诺教区</title><comment/></version><version><id>32698061</id><timestamp>2014年9月17日 (三) 08:27</timestamp><title>下阿穆爾州</title><comment/></version><version><id>32696011</id><timestamp>2014年9月17日 (三) 05:42</timestamp><title>黑姬山</title><comment/></version><version><id>32693335</id><timestamp>2014年9月17日 (三) 02:15</timestamp><title>蒂沃利</title><comment/></version><version><id>32686208</id><timestamp>2014年9月16日 (二) 15:01</timestamp><title>天主教奇維塔韋基亞-塔爾奎尼亞教區</title><comment/></version><version><id>32686149</id><timestamp>2014年9月16日 (二) 14:59</timestamp><title>User:Whhalbert/Sandbox 11</title><comment/></version><version><id>32686092</id><timestamp>2014年9月16日 (二) 14:56</timestamp><title>天主教奇維塔韋基亞-塔爾奎尼亞教區</title><comment/></version><version><id>32681457</id><timestamp>2014年9月16日 (二) 09:43</timestamp><title>天主教切雷托桑尼塔-泰萊塞-聖阿加塔德戈蒂教區</title><comment/></version><version><id>32681337</id><timestamp>2014年9月16日 (二) 09:25</timestamp><title>天主教切雷托桑尼塔-泰萊塞-聖阿加塔德戈蒂教區</title><comment/></version><version><id>32678057</id><timestamp>2014年9月16日 (二) 02:01</timestamp><title>User:Whhalbert/Sandbox 11</title><comment/></version><version><id>32677644</id><timestamp>2014年9月16日 (二) 00:51</timestamp><title>User:Whhalbert/Sandbox 11</title><comment/></version><version><id>32676554</id><timestamp>2014年9月15日 (一) 18:55</timestamp><title>User:Whhalbert/Sandbox 11</title><comment/></version><version><id>32675561</id><timestamp>2014年9月15日 (一) 17:15</timestamp><title>天主教维泰博教区</title><comment/></version><version><id>32675166</id><timestamp>2014年9月15日 (一) 16:44</timestamp><title>天主教维泰博教区</title><comment/></version><version><id>32673674</id><timestamp>2014年9月15日 (一) 15:01</timestamp><title>意大利天主教教区列表</title><comment/></version><version><id>32672028</id><timestamp>2014年9月15日 (一) 13:17</timestamp><title>天主教阿里亞諾伊爾皮諾-拉切多尼亞教區</title><comment/></version><version><id>32672012</id><timestamp>2014年9月15日 (一) 13:17</timestamp><title>天主教阿里亞諾伊爾皮諾-拉切多尼亞教區</title><comment/></version><version><id>32671261</id><timestamp>2014年9月15日 (一) 12:35</timestamp><title>意大利天主教教区列表</title><comment/></version><version><id>32671248</id><timestamp>2014年9月15日 (一) 12:34</timestamp><title>Template:意大利天主教教區</title><comment/></version><version><id>32668636</id><timestamp>2014年9月15日 (一) 09:21</timestamp><title>User:Whhalbert</title><comment/></version><version><id>32668536</id><timestamp>2014年9月15日 (一) 09:13</timestamp><title>天主教卢布林总教区</title><comment/></version><version><id>32668495</id><timestamp>2014年9月15日 (一) 09:10</timestamp><title>天主教卢布林总教区</title><comment/></version><version><id>32668485</id><timestamp>2014年9月15日 (一) 09:09</timestamp><title>天主教卢布林总教区</title><comment/></version><version><id>32668264</id><timestamp>2014年9月15日 (一) 08:55</timestamp><title>天主教赫爾辛基教區</title><comment/></version><version><id>32668248</id><timestamp>2014年9月15日 (一) 08:54</timestamp><title>天主教赫爾辛基教區</title><comment/></version><version><id>32665765</id><timestamp>2014年9月15日 (一) 06:02</timestamp><title>天主教阿韋利諾教區</title><comment/></version><version><id>32664381</id><timestamp>2014年9月15日 (一) 04:09</timestamp><title>易卜拉希姆·伊薩克·西德拉克</title><comment/></version><version><id>32664355</id><timestamp>2014年9月15日 (一) 04:06</timestamp><title>易卜拉希姆·伊薩克·西德拉克</title><comment/></version><version><id>32664347</id><timestamp>2014年9月15日 (一) 04:06</timestamp><title>涅爾謝斯·伯多祿十九世</title><comment/></version><version><id>32664331</id><timestamp>2014年9月15日 (一) 04:04</timestamp><title>涅爾謝斯·伯多祿十九世</title><comment/></version><version><id>32664326</id><timestamp>2014年9月15日 (一) 04:04</timestamp><title>易卜拉希姆·伊薩克·西德拉克</title><comment/></version><version><id>32664250</id><timestamp>2014年9月15日 (一) 03:57</timestamp><title>涅爾謝斯·伯多祿十九世</title><comment/></version><version><id>32655660</id><timestamp>2014年9月14日 (日) 12:04</timestamp><title>天主教弗利-貝爾蒂諾羅教區</title><comment/></version><version><id>32655653</id><timestamp>2014年9月14日 (日) 12:03</timestamp><title>天主教弗利-貝爾蒂諾羅教區</title><comment/></version><version><id>32655570</id><timestamp>2014年9月14日 (日) 11:57</timestamp><title>天主教切塞納-薩爾西納教區</title><comment/></version><version><id>32652213</id><timestamp>2014年9月14日 (日) 06:46</timestamp><title>天主教切塞納-薩爾西納教區</title><comment/></version><version><id>32652126</id><timestamp>2014年9月14日 (日) 06:38</timestamp><title>天主教切塞納-薩爾西納教區</title><comment/></version><version><id>32651968</id><timestamp>2014年9月14日 (日) 06:15</timestamp><title>天主教里米尼教區</title><comment/></version><version><id>32641442</id><timestamp>2014年9月13日 (六) 07:56</timestamp><title>天主教里米尼教區</title><comment/></version><version><id>32641429</id><timestamp>2014年9月13日 (六) 07:54</timestamp><title>天主教里米尼教區</title><comment/></version><version><id>32641147</id><timestamp>2014年9月13日 (六) 07:31</timestamp><title>天主教圣马力诺-蒙特费尔特罗教区</title><comment/></version><version><id>32641139</id><timestamp>2014年9月13日 (六) 07:30</timestamp><title>天主教圣马力诺-蒙特费尔特罗教区</title><comment/></version><version><id>32624203</id><timestamp>2014年9月11日 (四) 13:35</timestamp><title>天主教法諾-福松布羅內-卡利-佩爾戈拉教區</title><comment/></version><version><id>32624194</id><timestamp>2014年9月11日 (四) 13:34</timestamp><title>天主教法諾-福松布羅內-卡利-佩爾戈拉教區</title><comment/></version><version><id>32622157</id><timestamp>2014年9月11日 (四) 09:18</timestamp><title>天主教瓦洛-德拉盧卡尼亞教區</title><comment/></version><version><id>32622143</id><timestamp>2014年9月11日 (四) 09:16</timestamp><title>天主教瓦洛-德拉盧卡尼亞教區</title><comment/></version><version><id>32622060</id><timestamp>2014年9月11日 (四) 09:06</timestamp><title>天主教瓦洛-德拉盧卡尼亞教區</title><comment/></version><version><id>32622056</id><timestamp>2014年9月11日 (四) 09:04</timestamp><title>天主教瓦洛-德拉盧卡尼亞教區</title><comment/></version><version><id>32621859</id><timestamp>2014年9月11日 (四) 08:41</timestamp><title>User:Whhalbert/Sandbox 11</title><comment/></version><version><id>32616891</id><timestamp>2014年9月10日 (三) 17:38</timestamp><title>User:Whhalbert/Sandbox 11</title><comment/></version><version><id>32616881</id><timestamp>2014年9月10日 (三) 17:37</timestamp><title>天主教泰賈諾-波利卡斯特羅教區</title><comment/></version><version><id>32616770</id><timestamp>2014年9月10日 (三) 17:15</timestamp><title>天主教泰賈諾-波利卡斯特羅教區</title><comment/></version><version><id>32616764</id><timestamp>2014年9月10日 (三) 17:12</timestamp><title>天主教下諾切拉-薩爾諾教區</title><comment/></version><version><id>32616550</id><timestamp>2014年9月10日 (三) 16:35</timestamp><title>天主教下諾切拉-薩爾諾教區</title><comment/></version><version><id>32616011</id><timestamp>2014年9月10日 (三) 15:43</timestamp><title>天主教下諾切拉-薩爾諾教區</title><comment/></version><version><id>32615696</id><timestamp>2014年9月10日 (三) 15:04</timestamp><title>Template:意大利天主教教區</title><comment/></version><version><id>32609071</id><timestamp>2014年9月10日 (三) 01:29</timestamp><title>中哈關係</title><comment/></version><version><id>32607667</id><timestamp>2014年9月9日 (二) 16:54</timestamp><title>天主教盧切拉-特羅亞教區</title><comment/></version><version><id>32607364</id><timestamp>2014年9月9日 (二) 16:36</timestamp><title>天主教盧切拉-特羅亞教區</title><comment/></version><version><id>32607357</id><timestamp>2014年9月9日 (二) 16:35</timestamp><title>天主教盧切拉-特羅亞教區</title><comment/></version><version><id>32607144</id><timestamp>2014年9月9日 (二) 16:22</timestamp><title>天主教盧切拉-特羅亞教區</title><comment/></version><version><id>32606701</id><timestamp>2014年9月9日 (二) 15:28</timestamp><title>天主教拉努塞伊教區</title><comment/></version><version><id>32606687</id><timestamp>2014年9月9日 (二) 15:27</timestamp><title>天主教聖塞韋羅教區</title><comment/></version><version><id>32606668</id><timestamp>2014年9月9日 (二) 15:25</timestamp><title>天主教聖塞韋羅教區</title><comment/></version><version><id>32606663</id><timestamp>2014年9月9日 (二) 15:25</timestamp><title>天主教聖塞韋羅教區</title><comment/></version><version><id>32606650</id><timestamp>2014年9月9日 (二) 15:23</timestamp><title>天主教聖塞韋羅教區</title><comment/></version><version><id>32606422</id><timestamp>2014年9月9日 (二) 14:57</timestamp><title>派爾努甲醇悲劇</title><comment/></version><version><id>32591067</id><timestamp>2014年9月8日 (一) 05:04</timestamp><title>天主教切里尼奧拉-阿斯科利薩特里亞諾教區</title><comment/></version><version><id>32591016</id><timestamp>2014年9月8日 (一) 04:57</timestamp><title>天主教切里尼奧拉-阿斯科利薩特里亞諾教區</title><comment/></version><version><id>32587490</id><timestamp>2014年9月7日 (日) 17:05</timestamp><title>天主教烏真托-聖瑪利亞迪萊烏卡教區</title><comment/></version><version><id>32587471</id><timestamp>2014年9月7日 (日) 17:01</timestamp><title>天主教烏真托-聖瑪利亞迪萊烏卡教區</title><comment/></version><version><id>32587351</id><timestamp>2014年9月7日 (日) 16:44</timestamp><title>天主教納爾多-加利波利教區</title><comment/></version><version><id>32587122</id><timestamp>2014年9月7日 (日) 16:20</timestamp><title>天主教納爾多-加利波利教區</title><comment/></version><version><id>32587108</id><timestamp>2014年9月7日 (日) 16:17</timestamp><title>天主教納爾多-加利波利教區</title><comment/></version><version><id>32587104</id><timestamp>2014年9月7日 (日) 16:17</timestamp><title>天主教納爾多-加利波利教區</title><comment/></version><version><id>32586880</id><timestamp>2014年9月7日 (日) 15:51</timestamp><title>意大利天主教教区列表</title><comment/></version><version><id>32586865</id><timestamp>2014年9月7日 (日) 15:49</timestamp><title>Template:意大利天主教教區</title><comment/></version><version><id>32586783</id><timestamp>2014年9月7日 (日) 15:39</timestamp><title>天主教蒙特普齊亞諾-丘西-皮恩扎教區</title><comment/></version><version><id>32581152</id><timestamp>2014年9月7日 (日) 06:09</timestamp><title>天主教蒙特普齊亞諾-丘西-皮恩扎教區</title><comment/></version><version><id>32581138</id><timestamp>2014年9月7日 (日) 06:07</timestamp><title>天主教蒙特普齊亞諾-丘西-皮恩扎教區</title><comment/></version><version><id>32581122</id><timestamp>2014年9月7日 (日) 06:06</timestamp><title>天主教蒙特普齊亞諾-丘西-皮恩扎教區</title><comment/></version><version><id>32579678</id><timestamp>2014年9月7日 (日) 03:24</timestamp><title>天主教馬薩馬里蒂馬-皮翁比諾教區</title><comment/></version><version><id>32579524</id><timestamp>2014年9月7日 (日) 03:09</timestamp><title>天主教格羅塞托教區</title><comment/></version><version><id>32576505</id><timestamp>2014年9月6日 (六) 16:33</timestamp><title>天主教馬薩馬里蒂馬-皮翁比諾教區</title><comment/></version><version><id>32576390</id><timestamp>2014年9月6日 (六) 16:15</timestamp><title>天主教皮蒂利亞諾-索瓦納-奧爾貝泰洛教區</title><comment/></version><version><id>32573019</id><timestamp>2014年9月6日 (六) 10:17</timestamp><title>天主教皮蒂利亞諾-索瓦納-奧爾貝泰洛教區</title><comment/></version><version><id>32572187</id><timestamp>2014年9月6日 (六) 08:37</timestamp><title>因斯布魯克機場</title><comment/></version><version><id>32572183</id><timestamp>2014年9月6日 (六) 08:37</timestamp><title>因斯布魯克機場</title><comment/></version><version><id>32555196</id><timestamp>2014年9月4日 (四) 18:14</timestamp><title>天主教法布里亞諾-馬泰利卡教區</title><comment/></version><version><id>32555167</id><timestamp>2014年9月4日 (四) 18:05</timestamp><title>天主教法布里亞諾-馬泰利卡教區</title><comment/></version><version><id>32555159</id><timestamp>2014年9月4日 (四) 18:03</timestamp><title>天主教法布里亞諾-馬泰利卡教區</title><comment/></version><version><id>32555157</id><timestamp>2014年9月4日 (四) 18:02</timestamp><title>天主教法布里亞諾-馬泰利卡教區</title><comment/></version><version><id>32551651</id><timestamp>2014年9月4日 (四) 11:28</timestamp><title>中国动物志</title><comment/></version><version><id>32551648</id><timestamp>2014年9月4日 (四) 11:28</timestamp><title>中国动物志</title><comment/></version><version><id>32547159</id><timestamp>2014年9月4日 (四) 02:52</timestamp><title>天主教塞尼加利亞教區</title><comment/></version><version><id>32539567</id><timestamp>2014年9月3日 (三) 09:08</timestamp><title>天主教耶西教区</title><comment/></version><version><id>32539553</id><timestamp>2014年9月3日 (三) 09:07</timestamp><title>天主教耶西教区</title><comment/></version><version><id>32539197</id><timestamp>2014年9月3日 (三) 08:32</timestamp><title>天主教聖貝內代托-里帕特蘭索內-蒙塔爾托教區</title><comment/></version><version><id>32539187</id><timestamp>2014年9月3日 (三) 08:31</timestamp><title>天主教聖貝內代托-里帕特蘭索內-蒙塔爾托教區</title><comment/></version><version><id>32539024</id><timestamp>2014年9月3日 (三) 08:17</timestamp><title>Template:意大利天主教教區</title><comment/></version><version><id>32539021</id><timestamp>2014年9月3日 (三) 08:17</timestamp><title>意大利天主教教区列表</title><comment/></version><version><id>32538865</id><timestamp>2014年9月3日 (三) 07:58</timestamp><title>天主教沃爾泰拉教區</title><comment/></version><version><id>32538842</id><timestamp>2014年9月3日 (三) 07:56</timestamp><title>天主教沃爾泰拉教區</title><comment/></version><version><id>32537423</id><timestamp>2014年9月3日 (三) 05:27</timestamp><title>天主教佩夏教區</title><comment/></version><version><id>32536846</id><timestamp>2014年9月3日 (三) 04:27</timestamp><title>天主教佩夏教區</title><comment/></version><version><id>32536820</id><timestamp>2014年9月3日 (三) 04:23</timestamp><title>天主教佩夏教區</title><comment/></version><version><id>32536818</id><timestamp>2014年9月3日 (三) 04:22</timestamp><title>天主教佩夏教區</title><comment/></version><version><id>32533728</id><timestamp>2014年9月2日 (二) 17:24</timestamp><title>格拉斯哥大教堂</title><comment/></version><version><id>32533722</id><timestamp>2014年9月2日 (二) 17:23</timestamp><title>聖安德肋主教座堂 (格拉斯哥)</title><comment/></version><version><id>32533720</id><timestamp>2014年9月2日 (二) 17:22</timestamp><title>格拉斯哥大教堂</title><comment/></version><version><id>32533716</id><timestamp>2014年9月2日 (二) 17:21</timestamp><title>克拉科夫</title><comment/></version><version><id>32533619</id><timestamp>2014年9月2日 (二) 17:00</timestamp><title>天主教摩德纳-诺南托拉总教区</title><comment/></version><version><id>32533617</id><timestamp>2014年9月2日 (二) 17:00</timestamp><title>天主教馬薩卡拉拉-蓬特雷莫利教區</title><comment/></version><version><id>32533584</id><timestamp>2014年9月2日 (二) 16:54</timestamp><title>天主教摩德纳-诺南托拉总教区</title><comment/></version><version><id>32533351</id><timestamp>2014年9月2日 (二) 16:13</timestamp><title>意大利天主教教区列表</title><comment/></version><version><id>32533332</id><timestamp>2014年9月2日 (二) 16:11</timestamp><title>Template:意大利天主教教區</title><comment/></version><version><id>32529597</id><timestamp>2014年9月2日 (二) 09:56</timestamp><title>天主教里窝那教区</title><comment/></version><version><id>32529568</id><timestamp>2014年9月2日 (二) 09:54</timestamp><title>天主教里窝那教区</title><comment/></version><version><id>32529377</id><timestamp>2014年9月2日 (二) 09:40</timestamp><title>意大利天主教教区列表</title><comment/></version><version><id>32529238</id><timestamp>2014年9月2日 (二) 09:28</timestamp><title>天主教帕多瓦教區</title><comment/></version><version><id>32528554</id><timestamp/><title>昂熱大教堂</title><comment/></version><version><id>32528553</id><timestamp>2014年9月2日 (二) 08:31</timestamp><title>聖茂禮主教座堂 (昂熱)</title><comment/></version><version><id>32528464</id><timestamp>2014年9月2日 (二) 08:25</timestamp><title>天主教維羅納教區</title><comment/></version><version><id>32525795</id><timestamp>2014年9月2日 (二) 03:53</timestamp><title>澳門輕軌</title><comment/></version><version><id>32525464</id><timestamp>2014年9月2日 (二) 03:13</timestamp><title>圣保罗座堂</title><comment/></version><version><id>32525240</id><timestamp>2014年9月2日 (二) 02:46</timestamp><title>天主教維琴察教區</title><comment/></version><version><id>32525128</id><timestamp>2014年9月2日 (二) 02:33</timestamp><title>天主教維琴察教區</title><comment/></version><version><id>32525125</id><timestamp>2014年9月2日 (二) 02:32</timestamp><title>天主教維琴察教區</title><comment/></version><version><id>32524483</id><timestamp>2014年9月2日 (二) 01:18</timestamp><title>天主教韓國軍中教長區</title><comment/></version><version><id>32522223</id><timestamp>2014年9月1日 (一) 16:50</timestamp><title>天主教韓國軍中教長區</title><comment/></version><version><id>32522128</id><timestamp>2014年9月1日 (一) 16:39</timestamp><title>天主教韓國軍中教長區</title><comment/></version><version><id>32522120</id><timestamp>2014年9月1日 (一) 16:39</timestamp><title>天主教韓國軍中教長區</title><comment/></version><version><id>32522026</id><timestamp>2014年9月1日 (一) 16:25</timestamp><title>天主教基奧賈教區</title><comment/></version><version><id>32521959</id><timestamp>2014年9月1日 (一) 16:17</timestamp><title>天主教特雷維索教區</title><comment/></version><version><id>32519973</id><timestamp>2014年9月1日 (一) 13:17</timestamp><title>天主教基奧賈教區</title><comment/></version><version><id>32516370</id><timestamp>2014年9月1日 (一) 07:03</timestamp><title>周庭希</title><comment/></version><version><id>32516360</id><timestamp>2014年9月1日 (一) 07:03</timestamp><title>周庭希</title><comment/></version><version><id>32514026</id><timestamp>2014年9月1日 (一) 03:13</timestamp><title>白菜湯</title><comment/></version><version><id>32514019</id><timestamp>2014年9月1日 (一) 03:13</timestamp><title>白菜湯</title><comment/></version><version><id>32513331</id><timestamp>2014年9月1日 (一) 01:51</timestamp><title>酸辣湯</title><comment/></version><version><id>32513320</id><timestamp>2014年9月1日 (一) 01:49</timestamp><title>雜拌湯</title><comment/></version><version><id>32511730</id><timestamp>2014年8月31日 (日) 18:13</timestamp><title>哈爾格林姆教堂</title><comment/></version><version><id>32511726</id><timestamp>2014年8月31日 (日) 18:13</timestamp><title>哈爾格林姆教堂</title><comment/></version><version><id>32511686</id><timestamp>2014年8月31日 (日) 18:04</timestamp><title>哈薩克斯坦的俄羅斯人</title><comment/></version><version><id>32511684</id><timestamp>2014年8月31日 (日) 18:03</timestamp><title>哈薩克斯坦的俄羅斯人</title><comment/></version><version><id>32511675</id><timestamp>2014年8月31日 (日) 18:02</timestamp><title>札格瑞布主教座堂</title><comment/></version><version><id>32511666</id><timestamp>2014年8月31日 (日) 18:01</timestamp><title>札格瑞布主教座堂</title><comment/></version><version><id>32511638</id><timestamp>2014年8月31日 (日) 17:56</timestamp><title>博德博物馆</title><comment/></version><version><id>32511637</id><timestamp>2014年8月31日 (日) 17:56</timestamp><title>佩加蒙博物館</title><comment/></version><version><id>32511631</id><timestamp>2014年8月31日 (日) 17:55</timestamp><title>博德博物馆</title><comment/></version><version><id>32511603</id><timestamp>2014年8月31日 (日) 17:47</timestamp><title>柬埔寨伊斯蘭教</title><comment/></version><version><id>32511585</id><timestamp>2014年8月31日 (日) 17:44</timestamp><title>Category:葡萄牙银行</title><comment/></version><version><id>32511390</id><timestamp>2014年8月31日 (日) 17:16</timestamp><title>旧街场白咖啡</title><comment/></version><version><id>32511384</id><timestamp>2014年8月31日 (日) 17:15</timestamp><title>費城詢問報</title><comment/></version><version><id>32278661</id><timestamp>2014年8月15日 (五) 08:08</timestamp><title>正福寺天主堂</title><comment/></version><version><id>32278659</id><timestamp>2014年8月15日 (五) 08:08</timestamp><title>正福寺天主堂</title><comment/></version><version><id>32278631</id><timestamp>2014年8月15日 (五) 08:06</timestamp><title>正福寺天主堂</title><comment/></version><version><id>32277973</id><timestamp>2014年8月15日 (五) 07:11</timestamp><title>Wikipedia:互助客栈/方针</title><comment/></version><version><id>32264757</id><timestamp>2014年8月14日 (四) 05:22</timestamp><title>每天五個蘋果，普京遠離我</title><comment/></version><version><id>32240243</id><timestamp>2014年8月12日 (二) 07:26</timestamp><title>天主教阿斯科利皮切諾教區</title><comment/></version><version><id>32240229</id><timestamp>2014年8月12日 (二) 07:24</timestamp><title>天主教阿斯科利皮切諾教區</title><comment/></version><version><id>32228920</id><timestamp>2014年8月11日 (一) 09:24</timestamp><title>代代木上原</title><comment/></version><version><id>32220527</id><timestamp>2014年8月10日 (日) 15:05</timestamp><title>雜拌湯</title><comment/></version><version><id>32220406</id><timestamp>2014年8月10日 (日) 14:56</timestamp><title>雜拌湯</title><comment/></version><version><id>32220388</id><timestamp>2014年8月10日 (日) 14:55</timestamp><title>雜拌湯</title><comment/></version><version><id>32220366</id><timestamp>2014年8月10日 (日) 14:52</timestamp><title>雜拌湯</title><comment/></version><version><id>32196315</id><timestamp>2014年8月8日 (五) 16:22</timestamp><title>天主教阿德里亞-羅維戈教區</title><comment/></version><version><id>32196279</id><timestamp>2014年8月8日 (五) 16:18</timestamp><title>天主教阿德里亞-羅維戈教區</title><comment/></version><version><id>32196263</id><timestamp>2014年8月8日 (五) 16:17</timestamp><title>天主教阿德里亞-羅維戈教區</title><comment/></version><version><id>32191866</id><timestamp>2014年8月8日 (五) 09:39</timestamp><title>天主教貝盧諾-費爾特雷教區</title><comment/></version><version><id>32190905</id><timestamp>2014年8月8日 (五) 08:25</timestamp><title>若望保禄一世</title><comment/></version><version><id>32190874</id><timestamp>2014年8月8日 (五) 08:22</timestamp><title>天主教維托廖韋內托教區</title><comment/></version><version><id>32190822</id><timestamp>2014年8月8日 (五) 08:18</timestamp><title>天主教維托廖韋內托教區</title><comment/></version><version><id>32187121</id><timestamp>2014年8月8日 (五) 02:28</timestamp><title>Wikipedia:新条目推荐/候选</title><comment/></version><version><id>32187115</id><timestamp>2014年8月8日 (五) 02:27</timestamp><title>1994年青川金矿血案</title><comment/></version><version><id>32171329</id><timestamp>2014年8月7日 (四) 05:28</timestamp><title>文德郡</title><comment/></version><version><id>32168993</id><timestamp>2014年8月7日 (四) 01:46</timestamp><title>洛杉磯縣自然歷史博物館</title><comment/></version><version><id>32168970</id><timestamp>2014年8月7日 (四) 01:44</timestamp><title>拖姑清真寺</title><comment/></version><version><id>32168926</id><timestamp>2014年8月7日 (四) 01:40</timestamp><title>拖姑清真寺</title><comment/></version><version><id>32168901</id><timestamp>2014年8月7日 (四) 01:38</timestamp><title>拖姑清真寺</title><comment/></version><version><id>32166266</id><timestamp>2014年8月6日 (三) 15:42</timestamp><title>柚子胡椒</title><comment/></version><version><id>32166258</id><timestamp>2014年8月6日 (三) 15:41</timestamp><title>塔姆-劳里橡树</title><comment/></version><version><id>32144884</id><timestamp>2014年8月5日 (二) 01:48</timestamp><title>Wikipedia:新条目推荐/候选</title><comment/></version><version><id>32144870</id><timestamp>2014年8月5日 (二) 01:46</timestamp><title>Wikipedia:新条目推荐/候选</title><comment/></version><version><id>32132476</id><timestamp>2014年8月4日 (一) 01:45</timestamp><title>先知以利亚教堂 (塞萨洛尼基)</title><comment/></version><version><id>32094274</id><timestamp>2014年8月1日 (五) 01:45</timestamp><title>塞舌尔寿带</title><comment/></version><version><id>32094267</id><timestamp>2014年8月1日 (五) 01:44</timestamp><title>圣卡塔琳娜豚鼠</title><comment/></version><version><id>32081701</id><timestamp>2014年7月31日 (四) 03:33</timestamp><title>天主教康科迪亚-波代诺内教区</title><comment/></version><version><id>32081390</id><timestamp>2014年7月31日 (四) 03:07</timestamp><title>天主教康科迪亚-波代诺内教区</title><comment/></version><version><id>32081381</id><timestamp>2014年7月31日 (四) 03:06</timestamp><title>天主教康科迪亚-波代诺内教区</title><comment/></version><version><id>32081338</id><timestamp>2014年7月31日 (四) 03:04</timestamp><title>天主教康科迪亚-波代诺内教区</title><comment/></version><version><id>32080646</id><timestamp>2014年7月31日 (四) 02:00</timestamp><title>Template:意大利天主教教區</title><comment/></version><version><id>32077513</id><timestamp>2014年7月30日 (三) 15:00</timestamp><title>天主教帕爾馬教區</title><comment/></version><version><id>32077492</id><timestamp>2014年7月30日 (三) 14:58</timestamp><title>天主教帕爾馬教區</title><comment/></version><version><id>32076156</id><timestamp>2014年7月30日 (三) 13:23</timestamp><title>天主教圣马科阿尔真塔诺-斯卡莱阿教区</title><comment/></version><version><id>32076050</id><timestamp>2014年7月30日 (三) 13:16</timestamp><title>天主教圣马科阿尔真塔诺-斯卡莱阿教区</title><comment/></version><version><id>32075574</id><timestamp>2014年7月30日 (三) 12:36</timestamp><title>天主教圣马科阿尔真塔诺-斯卡莱阿教区</title><comment/></version><version><id>32075553</id><timestamp>2014年7月30日 (三) 12:34</timestamp><title>天主教圣马科阿尔真塔诺-斯卡莱阿教区</title><comment/></version><version><id>32075527</id><timestamp>2014年7月30日 (三) 12:32</timestamp><title>天主教圣马科阿尔真塔诺-斯卡莱阿教区</title><comment/></version><version><id>32073364</id><timestamp>2014年7月30日 (三) 09:29</timestamp><title>天主教圣马科阿尔真塔诺-斯卡莱阿教区</title><comment/></version><version><id>32073303</id><timestamp>2014年7月30日 (三) 09:26</timestamp><title>天主教卡薩諾阿洛約尼奧教區</title><comment/></version><version><id>32072710</id><timestamp>2014年7月30日 (三) 08:46</timestamp><title>天主教特里文托教區</title><comment/></version><version><id>32072695</id><timestamp>2014年7月30日 (三) 08:45</timestamp><title>天主教特里文托教區</title><comment/></version><version><id>32072655</id><timestamp>2014年7月30日 (三) 08:44</timestamp><title>天主教特里文托教區</title><comment/></version><version><id>32071839</id><timestamp>2014年7月30日 (三) 07:52</timestamp><title>天主教泰爾莫利-拉里諾教區</title><comment/></version><version><id>32071830</id><timestamp>2014年7月30日 (三) 07:51</timestamp><title>天主教伊塞爾尼亞-韋納夫羅教區</title><comment/></version><version><id>32071821</id><timestamp>2014年7月30日 (三) 07:51</timestamp><title>天主教泰爾莫利-拉里諾教區</title><comment/></version><version><id>32071312</id><timestamp>2014年7月30日 (三) 07:13</timestamp><title>天主教特里卡里科教区</title><comment/></version><version><id>32069837</id><timestamp>2014年7月30日 (三) 05:17</timestamp><title>加薩的波斐利</title><comment/></version><version><id>32069522</id><timestamp>2014年7月30日 (三) 04:43</timestamp><title>天主教梅爾菲-拉波拉-韋諾薩教區</title><comment/></version><version><id>32069514</id><timestamp>2014年7月30日 (三) 04:42</timestamp><title>天主教梅爾菲-拉波拉-韋諾薩教區</title><comment/></version><version><id>32069477</id><timestamp>2014年7月30日 (三) 04:38</timestamp><title>天主教梅爾菲-拉波拉-韋諾薩教區</title><comment/></version><version><id>32069451</id><timestamp>2014年7月30日 (三) 04:35</timestamp><title>天主教梅爾菲-拉波拉-韋諾薩教區</title><comment/></version><version><id>32069137</id><timestamp>2014年7月30日 (三) 03:59</timestamp><title>天主教圖爾西-拉戈內格羅教區</title><comment/></version><version><id>32069119</id><timestamp>2014年7月30日 (三) 03:57</timestamp><title>天主教圖爾西-拉戈內格羅教區</title><comment/></version><version><id>32069107</id><timestamp>2014年7月30日 (三) 03:56</timestamp><title>天主教圖爾西-拉戈內格羅教區</title><comment/></version><version><id>32068223</id><timestamp>2014年7月30日 (三) 02:50</timestamp><title>天主教伊塞爾尼亞-韋納夫羅教區</title><comment/></version><version><id>32067758</id><timestamp>2014年7月30日 (三) 02:16</timestamp><title>天主教伊塞爾尼亞-韋納夫羅教區</title><comment/></version><version><id>32067737</id><timestamp>2014年7月30日 (三) 02:15</timestamp><title>天主教伊塞爾尼亞-韋納夫羅教區</title><comment/></version><version><id>32066329</id><timestamp>2014年7月29日 (二) 23:31</timestamp><title>天主教滕皮奥-安普里亚斯教区</title><comment/></version><version><id>32066317</id><timestamp>2014年7月29日 (二) 23:28</timestamp><title>天主教滕皮奥-安普里亚斯教区</title><comment/></version><version><id>32062721</id><timestamp>2014年7月29日 (二) 14:10</timestamp><title>天主教滕皮奥-安普里亚斯教区</title><comment/></version><version><id>32061260</id><timestamp>2014年7月29日 (二) 12:39</timestamp><title>意大利天主教教区列表</title><comment/></version><version><id>32058868</id><timestamp>2014年7月29日 (二) 09:47</timestamp><title>天主教阿爾蓋羅-博薩教區</title><comment/></version><version><id>32058829</id><timestamp>2014年7月29日 (二) 09:44</timestamp><title>天主教奥齐耶里教区</title><comment/></version><version><id>32058813</id><timestamp>2014年7月29日 (二) 09:43</timestamp><title>天主教奥齐耶里教区</title><comment/></version><version><id>32058644</id><timestamp>2014年7月29日 (二) 09:29</timestamp><title>天主教奥齐耶里教区</title><comment/></version><version><id>32058417</id><timestamp>2014年7月29日 (二) 09:12</timestamp><title>天主教拉努塞伊教區</title><comment/></version><version><id>32057736</id><timestamp>2014年7月29日 (二) 08:09</timestamp><title>天主教努奧羅教區</title><comment/></version><version><id>32057716</id><timestamp>2014年7月29日 (二) 08:08</timestamp><title>天主教努奧羅教區</title><comment/></version><version><id>32057646</id><timestamp>2014年7月29日 (二) 08:02</timestamp><title>天主教努奧羅教區</title><comment/></version><version><id>32056965</id><timestamp>2014年7月29日 (二) 07:03</timestamp><title>天主教伊格萊西亞斯教區</title><comment/></version><version><id>32056191</id><timestamp>2014年7月29日 (二) 06:02</timestamp><title>天主教卡斯泰拉內塔教區</title><comment/></version><version><id>32055245</id><timestamp>2014年7月29日 (二) 04:29</timestamp><title>天主教奧里亞教區</title><comment/></version><version><id>32055160</id><timestamp>2014年7月29日 (二) 04:18</timestamp><title>天主教蘇爾莫納-瓦爾瓦教區</title><comment/></version><version><id>32054115</id><timestamp>2014年7月29日 (二) 02:39</timestamp><title>天主教蘇爾莫納-瓦爾瓦教區</title><comment/></version><version><id>32054096</id><timestamp>2014年7月29日 (二) 02:38</timestamp><title>宏伯特</title><comment/></version><version><id>32054080</id><timestamp>2014年7月29日 (二) 02:36</timestamp><title>天主教蘇爾莫納-瓦爾瓦教區</title><comment/></version><version><id>32054053</id><timestamp>2014年7月29日 (二) 02:33</timestamp><title>天主教蘇爾莫納-瓦爾瓦教區</title><comment/></version><version><id>32053454</id><timestamp>2014年7月29日 (二) 01:20</timestamp><title>天主教阿韋扎諾教區</title><comment/></version><version><id>32050348</id><timestamp>2014年7月28日 (一) 14:49</timestamp><title>天主教阿韋扎諾教區</title><comment/></version><version><id>32048463</id><timestamp>2014年7月28日 (一) 12:32</timestamp><title>天主教阿韋扎諾教區</title><comment/></version><version><id>32048456</id><timestamp>2014年7月28日 (一) 12:32</timestamp><title>天主教阿韋扎諾教區</title><comment/></version><version><id>32048431</id><timestamp>2014年7月28日 (一) 12:30</timestamp><title>天主教阿韋扎諾教區</title><comment/></version><version><id>32047085</id><timestamp>2014年7月28日 (一) 09:59</timestamp><title>天主教阿韋扎諾教區</title><comment/></version><version><id>32047072</id><timestamp>2014年7月28日 (一) 09:58</timestamp><title>天主教阿韋扎諾教區</title><comment/></version><version><id>32034591</id><timestamp>2014年7月27日 (日) 09:31</timestamp><title>天主教蘇薩教區</title><comment/></version><version><id>32034234</id><timestamp>2014年7月27日 (日) 08:58</timestamp><title>天主教亞歷山德里亞教區 (義大利)</title><comment/></version><version><id>32033649</id><timestamp>2014年7月27日 (日) 08:09</timestamp><title>天主教法諾-福松布羅內-卡利-佩爾戈拉教區</title><comment/></version><version><id>32031771</id><timestamp>2014年7月27日 (日) 04:51</timestamp><title>天主教拉梅齊亞泰爾梅教區</title><comment/></version><version><id>32031766</id><timestamp>2014年7月27日 (日) 04:50</timestamp><title>天主教拉梅齊亞泰爾梅教區</title><comment/></version><version><id>32031760</id><timestamp>2014年7月27日 (日) 04:49</timestamp><title>天主教拉梅齊亞泰爾梅教區</title><comment/></version><version><id>32031161</id><timestamp>2014年7月27日 (日) 03:44</timestamp><title>天主教福利尼奥教区</title><comment/></version><version><id>32030760</id><timestamp>2014年7月27日 (日) 03:01</timestamp><title>Wikipedia:互助客栈/方针</title><comment/></version><version><id>32030184</id><timestamp>2014年7月27日 (日) 01:50</timestamp><title>天主教古比奥教区</title><comment/></version><version><id>32028583</id><timestamp>2014年7月26日 (六) 18:55</timestamp><title>天主教馬扎拉-德爾瓦洛教區</title><comment/></version><version><id>32028467</id><timestamp>2014年7月26日 (六) 18:21</timestamp><title>天主教特拉帕尼教区</title><comment/></version><version><id>32028459</id><timestamp>2014年7月26日 (六) 18:20</timestamp><title>天主教特拉帕尼教区</title><comment/></version><version><id>32028258</id><timestamp>2014年7月26日 (六) 17:45</timestamp><title>意大利天主教教区列表</title><comment/></version><version><id>32028256</id><timestamp>2014年7月26日 (六) 17:45</timestamp><title>Template:意大利天主教教區</title><comment/></version><version><id>32027641</id><timestamp>2014年7月26日 (六) 16:12</timestamp><title>天主教卡尔塔吉罗内教区</title><comment/></version><version><id>32026838</id><timestamp>2014年7月26日 (六) 15:08</timestamp><title>天主教阿奇雷亞萊教區</title><comment/></version><version><id>32026258</id><timestamp>2014年7月26日 (六) 14:23</timestamp><title>天主教皮亞扎-阿爾梅里納教區</title><comment/></version><version><id>32026094</id><timestamp>2014年7月26日 (六) 14:09</timestamp><title>澳門觀察報</title><comment/></version><version><id>32025893</id><timestamp>2014年7月26日 (六) 13:52</timestamp><title>天主教卡爾塔尼塞塔教區</title><comment/></version><version><id>32025876</id><timestamp>2014年7月26日 (六) 13:51</timestamp><title>天主教卡爾塔尼塞塔教區</title><comment/></version><version><id>32024805</id><timestamp>2014年7月26日 (六) 12:09</timestamp><title>北方铁路 (智利)</title><comment/></version><version><id>32005807</id><timestamp>2014年7月25日 (五) 02:55</timestamp><title>天主教聖米尼亞托教區</title><comment/></version><version><id>32004914</id><timestamp>2014年7月25日 (五) 01:46</timestamp><title>印度－英国关系</title><comment/></version><version><id>32004858</id><timestamp>2014年7月25日 (五) 01:41</timestamp><title>印度－英国关系</title><comment/></version><version><id>31983325</id><timestamp>2014年7月23日 (三) 07:50</timestamp><title>荷兰高速铁路南线</title><comment/></version><version><id>31983315</id><timestamp>2014年7月23日 (三) 07:49</timestamp><title>荷兰高速铁路南线</title><comment/></version><version><id>31983306</id><timestamp>2014年7月23日 (三) 07:49</timestamp><title>荷兰高速铁路南线</title><comment/></version><version><id>31983299</id><timestamp>2014年7月23日 (三) 07:48</timestamp><title>芝加哥男孩</title><comment/></version><version><id>31964758</id><timestamp>2014年7月21日 (一) 14:17</timestamp><title>永生塔</title><comment/></version><version><id>31959457</id><timestamp>2014年7月21日 (一) 04:51</timestamp><title>摩苏尔</title><comment/></version><version><id>31955703</id><timestamp>2014年7月20日 (日) 16:54</timestamp><title>明尼亞波利斯訓練館</title><comment/></version><version><id>31938533</id><timestamp>2014年7月19日 (六) 04:49</timestamp><title>俄罗斯商队茶</title><comment/></version><version><id>31934840</id><timestamp>2014年7月18日 (五) 16:40</timestamp><title>天主教聖米尼亞托教區</title><comment/></version><version><id>31934834</id><timestamp>2014年7月18日 (五) 16:39</timestamp><title>天主教聖米尼亞托教區</title><comment/></version><version><id>31932029</id><timestamp>2014年7月18日 (五) 12:23</timestamp><title>天主教菲耶索萊教區</title><comment/></version><version><id>31931930</id><timestamp>2014年7月18日 (五) 12:12</timestamp><title>天主教阿雷佐-科爾托納-聖塞波爾克羅教區</title><comment/></version><version><id>31930736</id><timestamp>2014年7月18日 (五) 09:56</timestamp><title>天主教阿雷佐-科爾托納-聖塞波爾克羅教區</title><comment/></version><version><id>31930730</id><timestamp>2014年7月18日 (五) 09:55</timestamp><title>天主教阿雷佐-科爾托納-聖塞波爾克羅教區</title><comment/></version><version><id>31930724</id><timestamp>2014年7月18日 (五) 09:54</timestamp><title>天主教阿雷佐-科爾托納-聖塞波爾克羅教區</title><comment/></version><version><id>31930718</id><timestamp>2014年7月18日 (五) 09:53</timestamp><title>天主教阿雷佐-科爾托納-聖塞波爾克羅教區</title><comment/></version><version><id>31930286</id><timestamp>2014年7月18日 (五) 09:18</timestamp><title>天主教普拉托教區</title><comment/></version><version><id>31929041</id><timestamp>2014年7月18日 (五) 07:26</timestamp><title>天主教皮斯托亞教區</title><comment/></version><version><id>31928997</id><timestamp>2014年7月18日 (五) 07:21</timestamp><title>天主教亚历山德里亚教区</title><comment/></version><version><id>31928991</id><timestamp>2014年7月18日 (五) 07:21</timestamp><title>天主教亚历山德里亚教区</title><comment/></version><version><id>31928974</id><timestamp>2014年7月18日 (五) 07:19</timestamp><title>Template:意大利天主教教區</title><comment/></version><version><id>31928973</id><timestamp>2014年7月18日 (五) 07:18</timestamp><title>Template:美國天主教教區</title><comment/></version><version><id>31928968</id><timestamp>2014年7月18日 (五) 07:18</timestamp><title>天主教洛克里-傑拉切教區</title><comment/></version><version><id>31928966</id><timestamp>2014年7月18日 (五) 07:18</timestamp><title>天主教亚历山德里亚教区</title><comment/></version><version><id>31928965</id><timestamp>2014年7月18日 (五) 07:18</timestamp><title>天主教亚历山德里亚教区 (美国)</title><comment/></version><version><id>31928963</id><timestamp>2014年7月18日 (五) 07:18</timestamp><title>天主教米萊托-尼科泰拉-特羅佩阿教區</title><comment/></version><version><id>31928938</id><timestamp>2014年7月18日 (五) 07:16</timestamp><title>天主教泰拉莫-阿特里教區</title><comment/></version><version><id>31928934</id><timestamp>2014年7月18日 (五) 07:16</timestamp><title>天主教阿西西-諾切勞恩布拉-瓜爾多塔迪諾教區</title><comment/></version><version><id>31928925</id><timestamp>2014年7月18日 (五) 07:15</timestamp><title>天主教阿萊斯-泰拉爾巴教區</title><comment/></version><version><id>31928891</id><timestamp>2014年7月18日 (五) 07:13</timestamp><title>天主教皮斯托亞教區</title><comment/></version><version><id>31928692</id><timestamp>2014年7月18日 (五) 06:53</timestamp><title>Wikipedia:新条目推荐/候选</title><comment/></version><version><id>31928668</id><timestamp>2014年7月18日 (五) 06:50</timestamp><title>Wikipedia:新条目推荐/候选</title><comment/></version><version><id>31926891</id><timestamp>2014年7月18日 (五) 03:40</timestamp><title>天主教馬切拉塔-托倫蒂諾-雷卡納蒂-欽戈利-特雷伊阿教區</title><comment/></version><version><id>31926869</id><timestamp>2014年7月18日 (五) 03:37</timestamp><title>天主教馬切拉塔-托倫蒂諾-雷卡納蒂-欽戈利-特雷伊阿教區</title><comment/></version><version><id>31926344</id><timestamp>2014年7月18日 (五) 02:50</timestamp><title>天主教馬切拉塔-托倫蒂諾-雷卡納蒂-欽戈利-特雷伊阿教區</title><comment/></version><version><id>31926292</id><timestamp>2014年7月18日 (五) 02:44</timestamp><title>天主教馬切拉塔-托倫蒂諾-雷卡納蒂-欽戈利-特雷伊阿教區</title><comment/></version><version><id>31926177</id><timestamp>2014年7月18日 (五) 02:35</timestamp><title>天主教馬切拉塔-托倫蒂諾-雷卡納蒂-欽戈利-特雷伊阿教區</title><comment/></version><version><id>31926086</id><timestamp>2014年7月18日 (五) 02:25</timestamp><title>天主教馬切拉塔-托倫蒂諾-雷卡納蒂-欽戈利-特雷伊阿教區</title><comment/></version><version><id>31925737</id><timestamp>2014年7月18日 (五) 01:41</timestamp><title>天主教馬切拉塔-托倫蒂諾-雷卡納蒂-欽戈利-特雷伊阿教區</title><comment/></version><version><id>31925236</id><timestamp>2014年7月18日 (五) 00:35</timestamp><title>天主教馬切拉塔-托倫蒂諾-雷卡納蒂-欽戈利-特雷伊阿教區</title><comment/></version><version><id>31920336</id><timestamp>2014年7月17日 (四) 12:14</timestamp><title>Wikipedia:新条目推荐/候选</title><comment/></version></versions>
（最近 | 最旧） 查看（前500个 | 后500个）（20 | 50 | 100 | 250 | 500）
Whhalbert： 檢視子頁面 · 用户權限 · 編輯次數 ·  贡献报告 · 上傳的檔案（共享）·  所創條目 ·  跨語言活動 ·  SUL / 帐号 

取自“https://zh.wikipedia.org/wiki/Special:用户贡献”
		
	


	



	导航菜单
	
		

	
		个人工具
	
	
	
		
		没有登录讨论贡献创建账户登录
		
	


		
			

	
		名字空间
	
	
	
		
		特殊页面
		
	


			

	
	
		变种
	
	
	
		
		
		
	


		
		
			

	
		视图
	
	
	
		
		
		
	


			

	
	
		更多
	
	
	
		
		
		
	


			
	
		搜索
	
	
		
			
			
			
			
		
	


		
	
	

	
		
	
	

	
		导航
	
	
	
		
		首页分类索引特色内容新闻动态最近更改随机条目资助维基百科
		
	


	

	
		帮助
	
	
	
		
		帮助维基社群方针与指引互助客栈知识问答字词转换IRC即时聊天联络我们关于维基百科
		
	



	
		工具
	
	
	
		
		Atom用户贡献日志查看用户组上传文件特殊页面打印页面
		
	


	

	
		其他语言
	
	
	
		
		
		
	






	
	
	
		隐私政策
		关于维基百科
		免责声明
		手机版视图
		开发者
		统计
		Cookie声明
	
	
		
		
	
	



(RLQ=window.RLQ||[]).push(function(){mw.config.set({"wgBackendResponseTime":927,"wgHostname":"mw2268"});});
</user>
